Workbook

Sheet Cover
A1: Headcount & Operating Expense Planning Model — FY2027
A2: Built by Taruni Komma | Brightwater Analytics, Inc. (simulated ~70-person software company) | Monthly budget, Jan–Dec 2027
A4: KEY OUTPUTS (live, selected scenario)
A5: Scenario | B5: =Assumptions!C5 -> Plan
A6: Total FY2027 operating expense | B6: =Summary!B15 -> 15400173
A7: Over / (under) leadership ceiling | B7: =Summary!B17 -> 400172.93
A8: Opex as % of revenue | B8: =Summary!B19 -> 0.78975246
A9: Headcount: Jan 1 → Dec 31 | B9: =TEXT(Summary!F11,"0")&" → "&TEXT(Summary!G11,"0") -> 60 → 71
A10: New hires in plan | B10: =Summary!B24 -> 14
A11: People costs as % of opex | B11: =Summary!B23 -> 0.69249047
A12: Department budgets tie to total? | B12: =IF('Department Budget'!N96=0,"Yes","No — check") -> Yes
A14: HOW THE WORKBOOK IS ORGANIZED
A15: • Assumptions — scenario selector (B5), compensation rates, per-head costs, department drivers, targets
A16: • Roster — 60 employees and 18 open roles with salary, dates, and hiring priority
A17: • Headcount Calc — prorated FTE and salary for every person, every month (merit and departures included)
A18: • Department Budget — monthly budget by department and line item, rolled up to company total
A19: • Summary — FY2027 budget vs. FY2026 actual and the leadership ceiling, with a department chart
A20: • Scenarios — Plan, Hiring freeze, Accelerated growth and Deferred hiring side by side
A22: COLOR LEGEND
A23: Blue text — input
A24: Black text — formula
A25: Green text — link to another sheet
A26: Yellow fill — key lever

Sheet Assumptions
A1: Planning Assumptions — FY2027 (January–December 2027)
A2: Brightwater Analytics, Inc. is a simulated software company; all data is illustrative. Blue = input, yellow = key lever.
A4: SCENARIO
A5: Scenario selector (1 = Plan, 2 = Hiring freeze, 3 = Accelerated growth, 4 = Deferred hiring) | B5: 1 | C5: =CHOOSE($B$5,"Plan","Hiring freeze","Accelerated growth","Deferred hiring") -> Plan
A7: Lever | B7: Plan | C7: Hiring freeze | D7: Accelerated | E7: Deferred hiring | F7: Live
A8: Open roles approved (include priority ≤) | B8: 2 | C8: 1 | D8: 3 | E8: 2 | F8: =INDEX(B8:E8,Assumptions!$B$5) -> 2
A9: All hire start dates pulled forward (months) | B9: 0 | C9: 0 | D9: 1 | E9: 0 | F9: =INDEX(B9:E9,Assumptions!$B$5) -> 0
A10: Priority 2 hire start dates delayed (months) | B10: 0 | C10: 0 | D10: 0 | E10: 3 | F10: =INDEX(B10:E10,Assumptions!$B$5) -> 0
A11: Change to programs & vendor spend | B11: 0 | C11: -0.15 | D11: 0.1 | E11: -0.05 | F11: =INDEX(B11:E11,Assumptions!$B$5) -> 0
A12: Priority 1 = critical/backfill, 2 = planned growth, 3 = stretch. Freeze keeps only priority 1 roles.
A13: COMPENSATION & PER-HEAD COSTS
A14: Fiscal year start | B14: 46388
A15: Employer payroll taxes (% of salary) | B15: 0.072 | C15: Blended FICA, FUTA and state unemployment
A16: Benefits ($ per FTE per month) | B16: 1150 | C16: Medical, dental, 401(k) match
A17: Annual merit increase (existing employees) | B17: 0.035
A18: Merit effective date | B18: 46478
A19: Recruiting cost (% of new hire salary) | B19: 0.15 | C19: Agency and job-board costs
A20: Laptop and onboarding ($ per hire) | B20: 3000
A21: Software and tools ($ per FTE per month) | B21: 250
A22: Facilities allocation ($ per FTE per month) | B22: 600
A23: Sales on-target variable compensation (% of salary) | B23: 0.3 | C23: Replaces the level bonus for Sales
A25: BONUS TARGET BY LEVEL (% of salary)
A26: Level | B26: Bonus %
A27: 1 | B27: 0.05
A28: 2 | B28: 0.08
A29: 3 | B29: 0.1
A30: 4 | B30: 0.15
A31: 5 | B31: 0.2
A33: DEPARTMENT COST DRIVERS
A34: Department | B34: Travel & entertainment ($/FTE/mo) | C34: Programs & vendors (annual $) | D34: Programs include
A35: Engineering | B35: 150 | C35: 600000 | D35: Dev tools, cloud test environments, contractors
A36: Product | B36: 200 | C36: 100000 | D36: User research, design tools
A37: Sales | B37: 1200 | C37: 300000 | D37: CRM seats, sales events, data providers
A38: Marketing | B38: 400 | C38: 1400000 | D38: Paid media, events, content agencies
A39: Customer Success | B39: 200 | C39: 150000 | D39: Support platform, training
A40: G&A | B40: 150 | C40: 900000 | D40: Audit, legal, insurance, HR systems
A42: COMPANY TARGETS
A43: FY2027 revenue plan ($) | B43: 19500000 | C43: Board-approved plan
A44: FY2026 revenue actual ($) | B44: 15000000
A45: Leadership operating expense ceiling ($) | B45: 15000000 | C45: Maximum FY2027 opex approved by leadership

Sheet Roster
A1: Employee Roster and Hiring Plan
A2: 60 current employees and 18 open roles. Edit salaries, dates or priorities here (blue); the model updates automatically. Simulated data — employee IDs only.
A5: Employee ID | B5: Department | C5: Title | D5: Level | E5: Status | F5: Annual salary ($) | G5: Start date | H5: End date | I5: Priority | J5: Note
A6: ENG-101 | B6: Engineering | C6: Software Engineer I | D6: 1 | E6: Existing | F6: 84500 | G6: 44713
A7: ENG-102 | B7: Engineering | C7: Software Engineer I | D7: 1 | E7: Existing | F7: 81000 | G7: 45962
A8: ENG-103 | B8: Engineering | C8: Software Engineer I | D8: 1 | E8: Existing | F8: 86000 | G8: 43922
A9: ENG-104 | B9: Engineering | C9: Software Engineer I | D9: 1 | E9: Existing | F9: 79500 | G9: 45170
A10: ENG-105 | B10: Engineering | C10: Software Engineer II | D10: 2 | E10: Existing | F10: 110500 | G10: 46054
A11: ENG-106 | B11: Engineering | C11: Software Engineer II | D11: 2 | E11: Existing | F11: 108000 | G11: 44378
A12: ENG-107 | B12: Engineering | C12: Software Engineer II | D12: 2 | E12: Existing | F12: 112500 | G12: 45627
A13: ENG-108 | B13: Engineering | C13: Software Engineer II | D13: 2 | E13: Existing | F13: 109000 | G13: 43586
A14: ENG-109 | B14: Engineering | C14: Software Engineer II | D14: 2 | E14: Existing | F14: 111500 | G14: 44835
A15: ENG-110 | B15: Engineering | C15: Software Engineer II | D15: 2 | E15: Existing | F15: 107000 | G15: 45717
A16: ENG-111 | B16: Engineering | C16: Senior Software Engineer | D16: 3 | E16: Existing | F16: 153000 | G16: 44044 | H16: 46507 | J16: Departing — backfill planned
A17: ENG-112 | B17: Engineering | C17: Senior Software Engineer | D17: 3 | E17: Existing | F17: 141500 | G17: 44927
A18: ENG-113 | B18: Engineering | C18: Senior Software Engineer | D18: 3 | E18: Existing | F18: 148500 | G18: 46174
A19: ENG-114 | B19: Engineering | C19: Senior Software Engineer | D19: 3 | E19: Existing | F19: 145500 | G19: 44501
A20: ENG-115 | B20: Engineering | C20: Senior Software Engineer | D20: 3 | E20: Existing | F20: 151500 | G20: 45383
A21: ENG-116 | B21: Engineering | C21: Senior Software Engineer | D21: 3 | E21: Existing | F21: 147000 | G21: 43709
A22: ENG-117 | B22: Engineering | C22: Staff Engineer | D22: 4 | E22: Existing | F22: 193500 | G22: 44593
A23: ENG-118 | B23: Engineering | C23: Staff Engineer | D23: 4 | E23: Existing | F23: 186000 | G23: 45839
A24: ENG-119 | B24: Engineering | C24: Staff Engineer | D24: 4 | E24: Existing | F24: 197500 | G24: 44166
A25: ENG-120 | B25: Engineering | C25: Director of Engineering | D25: 5 | E25: Existing | F25: 243000 | G25: 45047
A26: PRD-101 | B26: Product | C26: Product Manager | D26: 2 | E26: Existing | F26: 100500 | G26: 45809
A27: PRD-102 | B27: Product | C27: Product Manager | D27: 2 | E27: Existing | F27: 105500 | G27: 44136
A28: PRD-103 | B28: Product | C28: Senior Product Manager | D28: 3 | E28: Existing | F28: 139500 | G28: 45017
... A35: SLS-105 | B35: Sales | C35: Account Executive | D35: 2 | E35: Existing | F35: 84000 | G35: 45323
A36: SLS-106 | B36: Sales | C36: Account Executive | D36: 2 | E36: Existing | F36: 77500 | G36: 43647 | H36: 46568 | J36: Departing — backfill planned
A37: SLS-107 | B37: Sales | C37: Account Executive | D37: 2 | E37: Existing | F37: 81500 | G37: 44896
A38: SLS-108 | B38: Sales | C38: Account Executive | D38: 2 | E38: Existing | F38: 80000 | G38: 45778
A39: SLS-109 | B39: Sales | C39: Senior Account Executive | D39: 3 | E39: Existing | F39: 112000 | G39: 44105
A40: SLS-110 | B40: Sales | C40: Senior Account Executive | D40: 3 | E40: Existing | F40: 109000 | G40: 44986
A41: SLS-111 | B41: Sales | C41: Sales Manager | D41: 4 | E41: Existing | F41: 143000 | G41: 46235
A42: SLS-112 | B42: Sales | C42: VP, Sales | D42: 5 | E42: Existing | F42: 183500 | G42: 44197
A43: MKT-101 | B43: Marketing | C43: Marketing Coordinator | D43: 1 | E43: Existing | F43: 67000 | G43: 45078
A44: MKT-102 | B44: Marketing | C44: Marketing Coordinator | D44: 1 | E44: Existing | F44: 71000 | G44: 46327
A45: MKT-103 | B45: Marketing | C45: Marketing Manager | D45: 2 | E45: Existing | F45: 86500 | G45: 44287
A46: MKT-104 | B46: Marketing | C46: Marketing Manager | D46: 2 | E46: Existing | F46: 91000 | G46: 45536
A47: MKT-105 | B47: Marketing | C47: Director of Marketing | D47: 4 | E47: Existing | F47: 155000 | G47: 43497
A48: MKT-106 | B48: Marketing | C48: VP, Marketing | D48: 5 | E48: Existing | F48: 215500 | G48: 44743
A49: CSX-101 | B49: Customer Success | C49: Support Specialist | D49: 1 | E49: Existing | F49: 62000 | G49: 46174
A50: CSX-102 | B50: Customer Success | C50: Support Specialist | D50: 1 | E50: Existing | F50: 60500 | G50: 44501 | H50: 46630 | J50: Departing — backfill planned
A51: CSX-103 | B51: Customer Success | C51: Support Specialist | D51: 1 | E51: Existing | F51: 63000 | G51: 45383
A52: CSX-104 | B52: Customer Success | C52: Support Specialist | D52: 1 | E52: Existing | F52: 61000 | G52: 43709
A53: CSX-105 | B53: Customer Success | C53: Customer Success Manager | D53: 2 | E53: Existing | F53: 82500 | G53: 44593
A54: CSX-106 | B54: Customer Success | C54: Customer Success Manager | D54: 2 | E54: Existing | F54: 79000 | G54: 45839
A55: CSX-107 | B55: Customer Success | C55: Customer Success Manager | D55: 2 | E55: Existing | F55: 84000 | G55: 44166
A56: CSX-108 | B56: Customer Success | C56: Senior Customer Success Manager | D56: 3 | E56: Existing | F56: 104500 | G56: 45047
A57: CSX-109 | B57: Customer Success | C57: Customer Success Lead | D57: 4 | E57: Existing | F57: 141500 | G57: 46296
A58: GNA-101 | B58: G&A | C58: Staff Accountant | D58: 1 | E58: Existing | F58: 68500 | G58: 44348
A59: GNA-102 | B59: G&A | C59: Staff Accountant | D59: 1 | E59: Existing | F59: 70000 | G59: 45597
A60: GNA-103 | B60: G&A | C60: Financial Analyst | D60: 2 | E60: Existing | F60: 88500 | G60: 43556
A61: GNA-104 | B61: G&A | C61: Financial Analyst | D61: 2 | E61: Existing | F61: 94000 | G61: 44805
A62: GNA-105 | B62: G&A | C62: Senior Accountant | D62: 3 | E62: Existing | F62: 116500 | G62: 45689
... A65: GNA-108 | B65: G&A | C65: Chief Financial Officer | D65: 5 | E65: Existing | F65: 215500 | G65: 46143
A66: TBH-ENG-01 | B66: Engineering | C66: Software Engineer II | D66: 2 | E66: Open role | F66: 108000 | G66: 46419 | I66: 1 | J66: Platform team capacity
A67: TBH-ENG-02 | B67: Engineering | C67: Senior Software Engineer | D67: 3 | E67: Open role | F67: 151500 | G67: 46508 | I67: 1 | J67: Backfill for departing senior engineer
A68: TBH-ENG-03 | B68: Engineering | C68: Software Engineer II | D68: 2 | E68: Open role | F68: 109000 | G68: 46478 | I68: 2 | J68: Data pipeline roadmap
A69: TBH-ENG-04 | B69: Engineering | C69: Senior Software Engineer | D69: 3 | E69: Open role | F69: 150000 | G69: 46539 | I69: 2 | J69: Security and compliance work
A70: TBH-ENG-05 | B70: Engineering | C70: Staff Engineer | D70: 4 | E70: Open role | F70: 186000 | G70: 46569 | I70: 2 | J70: Machine learning lead
A71: TBH-ENG-06 | B71: Engineering | C71: Software Engineer I | D71: 1 | E71: Open role | F71: 86000 | G71: 46631 | I71: 3 | J71: Junior capacity for H2 roadmap
A72: TBH-PRD-01 | B72: Product | C72: Senior Product Manager | D72: 3 | E72: Open role | F72: 139500 | G72: 46447 | I72: 2 | J72: Second product line
A73: TBH-SLS-01 | B73: Sales | C73: Account Executive | D73: 2 | E73: Open role | F73: 80000 | G73: 46447 | I73: 1 | J73: New enterprise territory
A74: TBH-SLS-02 | B74: Sales | C74: Account Executive | D74: 2 | E74: Open role | F74: 83000 | G74: 46569 | I74: 1 | J74: Backfill for departing account executive
A75: TBH-SLS-03 | B75: Sales | C75: Account Executive | D75: 2 | E75: Open role | F75: 81000 | G75: 46539 | I75: 2 | J75: Mid-market expansion
A76: TBH-SLS-04 | B76: Sales | C76: Sales Development Rep | D76: 1 | E76: Open role | F76: 62500 | G76: 46631 | I76: 3 | J76: Pipeline generation
A77: TBH-MKT-01 | B77: Marketing | C77: Marketing Manager | D77: 2 | E77: Open role | F77: 89500 | G77: 46478 | I77: 2 | J77: Demand generation
... A83: TBH-GNA-02 | B83: G&A | C83: Financial Analyst | D83: 2 | E83: Open role | F83: 93000 | G83: 46539 | I83: 2 | J83: FP&A and planning support

Sheet Headcount Calc
A1: Monthly FTE and Salary Engine
A2: FTE is prorated by days employed in each month. Salaries include the merit increase from its effective date for employees hired before the fiscal year.
K3: FTE by month | W3: Salary cost by month ($)
A5: Employee ID | B5: Department | C5: Status | D5: Level | E5: Annual salary | F5: Scenario start | G5: End date | H5: In plan (1/0) | I5: Bonus % | J5: Merit eligible | K5: =DATE(YEAR(Assumptions!$B$14),MONTH(Assumptions!$B$14)+0,1) -> 46388 | L5: =DATE(YEAR(Assumptions!$B$14),MONTH(Assumptions!$B$14)+1,1) -> 46419 | M5: =DATE(YEAR(Assumptions!$B$14),MONTH(Assumptions!$B$14)+2,1) -> 46447 | N5: =DATE(YEAR(Assumptions!$B$14),MONTH(Assumptions!$B$14)+3,1) -> 46478 | O5: =DATE(YEAR(Assumptions!$B$14),MONTH(Assumptions!$B$14)+4,1) -> 46508 | P5: =DATE(YEAR(Assumptions!$B$14),MONTH(Assumptions!$B$14)+5,1) -> 46539 | Q5: =DATE(YEAR(Assumptions!$B$14),MONTH(Assumptions!$B$14)+6,1) -> 46569 | R5: =DATE(YEAR(Assumptions!$B$14),MONTH(Assumptions!$B$14)+7,1) -> 46600 | S5: =DATE(YEAR(Assumptions!$B$14),MONTH(Assumptions!$B$14)+8,1) -> 46631 | T5: =DATE(YEAR(Assumptions!$B$14),MONTH(Assumptions!$B$14)+9,1) -> 46661 | U5: =DATE(YEAR(Assumptions!$B$14),MONTH(Assumptions!$B$14)+10,1) -> 46692 | V5: =DATE(YEAR(Assumptions!$B$14),MONTH(Assumptions!$B$14)+11,1) -> 46722 | W5: =DATE(YEAR(Assumptions!$B$14),MONTH(Assumptions!$B$14)+0,1) -> 46388 | X5: =DATE(YEAR(Assumptions!$B$14),MONTH(Assumptions!$B$14)+1,1) -> 46419 | Y5: =DATE(YEAR(Assumptions!$B$14),MONTH(Assumptions!$B$14)+2,1) -> 46447 | Z5: =DATE(YEAR(Assumptions!$B$14),MONTH(Assumptions!$B$14)+3,1) -> 46478 | AA5: =DATE(YEAR(Assumptions!$B$14),MONTH(Assumptions!$B$14)+4,1) -> 46508 | AB5: =DATE(YEAR(Assumptions!$B$14),MONTH(Assumptions!$B$14)+5,1) -> 46539 | AC5: =DATE(YEAR(Assumptions!$B$14),MONTH(Assumptions!$B$14)+6,1) -> 46569 | AD5: =DATE(YEAR(Assumptions!$B$14),MONTH(Assumptions!$B$14)+7,1) -> 46600 | AE5: =DATE(YEAR(Assumptions!$B$14),MONTH(Assumptions!$B$14)+8,1) -> 46631 | AF5: =DATE(YEAR(Assumptions!$B$14),MONTH(Assumptions!$B$14)+9,1) -> 46661 | AG5: =DATE(YEAR(Assumptions!$B$14),MONTH(Assumptions!$B$14)+10,1) -> 46692 | AH5: =DATE(YEAR(Assumptions!$B$14),MONTH(Assumptions!$B$14)+11,1) -> 46722
A6: =Roster!A6 -> ENG-101 | B6: =Roster!B6 -> Engineering | C6: =Roster!E6 -> Existing | D6: =Roster!D6 -> 1 | E6: =Roster!F6 -> 84500 | F6: =IF(Roster!E6="Open role",MAX(Assumptions!$B$14,EDATE(Roster!G6,IF(Roster!I6=2,Assumptions!$F$10,0)-Assumptions!$F$9)),Roster!G6) -> 44713 | G6: =IF(Roster!H6="",DATE(2099,12,31),Roster!H6) -> 73050 | H6: =IF(Roster!E6="Existing",1,IF(Roster!I6<=Assumptions!$F$8,1,0)) -> 1 | I6: =IF(B6="Sales",Assumptions!$B$23,VLOOKUP(D6,Assumptions!$A$27:$B$31,2,FALSE())) -> 0.05 | J6: =IF(F6<Assumptions!$B$14,1,0) -> 1 | K6: =IF($H6=1,MAX(0,MIN($G6,EOMONTH(K$5,0))-MAX($F6,K$5)+1)/DAY(EOMONTH(K$5,0)),0) -> 1 | L6: =IF($H6=1,MAX(0,MIN($G6,EOMONTH(L$5,0))-MAX($F6,L$5)+1)/DAY(EOMONTH(L$5,0)),0) -> 1 | M6: =IF($H6=1,MAX(0,MIN($G6,EOMONTH(M$5,0))-MAX($F6,M$5)+1)/DAY(EOMONTH(M$5,0)),0) -> 1 | N6: =IF($H6=1,MAX(0,MIN($G6,EOMONTH(N$5,0))-MAX($F6,N$5)+1)/DAY(EOMONTH(N$5,0)),0) -> 1 | O6: =IF($H6=1,MAX(0,MIN($G6,EOMONTH(O$5,0))-MAX($F6,O$5)+1)/DAY(EOMONTH(O$5,0)),0) -> 1 | P6: =IF($H6=1,MAX(0,MIN($G6,EOMONTH(P$5,0))-MAX($F6,P$5)+1)/DAY(EOMONTH(P$5,0)),0) -> 1 | Q6: =IF($H6=1,MAX(0,MIN($G6,EOMONTH(Q$5,0))-MAX($F6,Q$5)+1)/DAY(EOMONTH(Q$5,0)),0) -> 1 | R6: =IF($H6=1,MAX(0,MIN($G6,EOMONTH(R$5,0))-MAX($F6,R$5)+1)/DAY(EOMONTH(R$5,0)),0) -> 1 | ... V6: =IF($H6=1,MAX(0,MIN($G6,EOMONTH(V$5,0))-MAX($F6,V$5)+1)/DAY(EOMONTH(V$5,0)),0) -> 1 | W6: =$E6/12*K6*IF(AND($J6=1,W$5>=Assumptions!$B$18),1+Assumptions!$B$17,1) -> 7041.6667 | X6: =$E6/12*L6*IF(AND($J6=1,X$5>=Assumptions!$B$18),1+Assumptions!$B$17,1) -> 7041.6667 | Y6: =$E6/12*M6*IF(AND($J6=1,Y$5>=Assumptions!$B$18),1+Assumptions!$B$17,1) -> 7041.6667 | Z6: =$E6/12*N6*IF(AND($J6=1,Z$5>=Assumptions!$B$18),1+Assumptions!$B$17,1) -> 7288.125 | AA6: =$E6/12*O6*IF(AND($J6=1,AA$5>=Assumptions!$B$18),1+Assumptions!$B$17,1) -> 7288.125 | AB6: =$E6/12*P6*IF(AND($J6=1,AB$5>=Assumptions!$B$18),1+Assumptions!$B$17,1) -> 7288.125 | AC6: =$E6/12*Q6*IF(AND($J6=1,AC$5>=Assumptions!$B$18),1+Assumptions!$B$17,1) -> 7288.125 | AD6: =$E6/12*R6*IF(AND($J6=1,AD$5>=Assumptions!$B$18),1+Assumptions!$B$17,1) -> 7288.125 | ... AH6: =$E6/12*V6*IF(AND($J6=1,AH$5>=Assumptions!$B$18),1+Assumptions!$B$17,1) -> 7288.125
A7: =Roster!A7 -> ENG-102 | B7: =Roster!B7 -> Engineering | C7: =Roster!E7 -> Existing | D7: =Roster!D7 -> 1 | E7: =Roster!F7 -> 81000 | F7: =IF(Roster!E7="Open role",MAX(Assumptions!$B$14,EDATE(Roster!G7,IF(Roster!I7=2,Assumptions!$F$10,0)-Assumptions!$F$9)),Roster!G7) -> 45962 | G7: =IF(Roster!H7="",DATE(2099,12,31),Roster!H7) -> 73050 | H7: =IF(Roster!E7="Existing",1,IF(Roster!I7<=Assumptions!$F$8,1,0)) -> 1 | I7: =IF(B7="Sales",Assumptions!$B$23,VLOOKUP(D7,Assumptions!$A$27:$B$31,2,FALSE())) -> 0.05 | J7: =IF(F7<Assumptions!$B$14,1,0) -> 1 | K7: =IF($H7=1,MAX(0,MIN($G7,EOMONTH(K$5,0))-MAX($F7,K$5)+1)/DAY(EOMONTH(K$5,0)),0) -> 1 | L7: =IF($H7=1,MAX(0,MIN($G7,EOMONTH(L$5,0))-MAX($F7,L$5)+1)/DAY(EOMONTH(L$5,0)),0) -> 1 | M7: =IF($H7=1,MAX(0,MIN($G7,EOMONTH(M$5,0))-MAX($F7,M$5)+1)/DAY(EOMONTH(M$5,0)),0) -> 1 | N7: =IF($H7=1,MAX(0,MIN($G7,EOMONTH(N$5,0))-MAX($F7,N$5)+1)/DAY(EOMONTH(N$5,0)),0) -> 1 | O7: =IF($H7=1,MAX(0,MIN($G7,EOMONTH(O$5,0))-MAX($F7,O$5)+1)/DAY(EOMONTH(O$5,0)),0) -> 1 | P7: =IF($H7=1,MAX(0,MIN($G7,EOMONTH(P$5,0))-MAX($F7,P$5)+1)/DAY(EOMONTH(P$5,0)),0) -> 1 | Q7: =IF($H7=1,MAX(0,MIN($G7,EOMONTH(Q$5,0))-MAX($F7,Q$5)+1)/DAY(EOMONTH(Q$5,0)),0) -> 1 | R7: =IF($H7=1,MAX(0,MIN($G7,EOMONTH(R$5,0))-MAX($F7,R$5)+1)/DAY(EOMONTH(R$5,0)),0) -> 1 | ... V7: =IF($H7=1,MAX(0,MIN($G7,EOMONTH(V$5,0))-MAX($F7,V$5)+1)/DAY(EOMONTH(V$5,0)),0) -> 1 | W7: =$E7/12*K7*IF(AND($J7=1,W$5>=Assumptions!$B$18),1+Assumptions!$B$17,1) -> 6750 | X7: =$E7/12*L7*IF(AND($J7=1,X$5>=Assumptions!$B$18),1+Assumptions!$B$17,1) -> 6750 | Y7: =$E7/12*M7*IF(AND($J7=1,Y$5>=Assumptions!$B$18),1+Assumptions!$B$17,1) -> 6750 | Z7: =$E7/12*N7*IF(AND($J7=1,Z$5>=Assumptions!$B$18),1+Assumptions!$B$17,1) -> 6986.25 | AA7: =$E7/12*O7*IF(AND($J7=1,AA$5>=Assumptions!$B$18),1+Assumptions!$B$17,1) -> 6986.25 | AB7: =$E7/12*P7*IF(AND($J7=1,AB$5>=Assumptions!$B$18),1+Assumptions!$B$17,1) -> 6986.25 | AC7: =$E7/12*Q7*IF(AND($J7=1,AC$5>=Assumptions!$B$18),1+Assumptions!$B$17,1) -> 6986.25 | AD7: =$E7/12*R7*IF(AND($J7=1,AD$5>=Assumptions!$B$18),1+Assumptions!$B$17,1) -> 6986.25 | ... AH7: =$E7/12*V7*IF(AND($J7=1,AH$5>=Assumptions!$B$18),1+Assumptions!$B$17,1) -> 6986.25
A8: =Roster!A8 -> ENG-103 | B8: =Roster!B8 -> Engineering | C8: =Roster!E8 -> Existing | D8: =Roster!D8 -> 1 | E8: =Roster!F8 -> 86000 | F8: =IF(Roster!E8="Open role",MAX(Assumptions!$B$14,EDATE(Roster!G8,IF(Roster!I8=2,Assumptions!$F$10,0)-Assumptions!$F$9)),Roster!G8) -> 43922 | G8: =IF(Roster!H8="",DATE(2099,12,31),Roster!H8) -> 73050 | H8: =IF(Roster!E8="Existing",1,IF(Roster!I8<=Assumptions!$F$8,1,0)) -> 1 | I8: =IF(B8="Sales",Assumptions!$B$23,VLOOKUP(D8,Assumptions!$A$27:$B$31,2,FALSE())) -> 0.05 | J8: =IF(F8<Assumptions!$B$14,1,0) -> 1 | K8: =IF($H8=1,MAX(0,MIN($G8,EOMONTH(K$5,0))-MAX($F8,K$5)+1)/DAY(EOMONTH(K$5,0)),0) -> 1 | L8: =IF($H8=1,MAX(0,MIN($G8,EOMONTH(L$5,0))-MAX($F8,L$5)+1)/DAY(EOMONTH(L$5,0)),0) -> 1 | M8: =IF($H8=1,MAX(0,MIN($G8,EOMONTH(M$5,0))-MAX($F8,M$5)+1)/DAY(EOMONTH(M$5,0)),0) -> 1 | N8: =IF($H8=1,MAX(0,MIN($G8,EOMONTH(N$5,0))-MAX($F8,N$5)+1)/DAY(EOMONTH(N$5,0)),0) -> 1 | O8: =IF($H8=1,MAX(0,MIN($G8,EOMONTH(O$5,0))-MAX($F8,O$5)+1)/DAY(EOMONTH(O$5,0)),0) -> 1 | P8: =IF($H8=1,MAX(0,MIN($G8,EOMONTH(P$5,0))-MAX($F8,P$5)+1)/DAY(EOMONTH(P$5,0)),0) -> 1 | Q8: =IF($H8=1,MAX(0,MIN($G8,EOMONTH(Q$5,0))-MAX($F8,Q$5)+1)/DAY(EOMONTH(Q$5,0)),0) -> 1 | R8: =IF($H8=1,MAX(0,MIN($G8,EOMONTH(R$5,0))-MAX($F8,R$5)+1)/DAY(EOMONTH(R$5,0)),0) -> 1 | ... V8: =IF($H8=1,MAX(0,MIN($G8,EOMONTH(V$5,0))-MAX($F8,V$5)+1)/DAY(EOMONTH(V$5,0)),0) -> 1 | W8: =$E8/12*K8*IF(AND($J8=1,W$5>=Assumptions!$B$18),1+Assumptions!$B$17,1) -> 7166.6667 | X8: =$E8/12*L8*IF(AND($J8=1,X$5>=Assumptions!$B$18),1+Assumptions!$B$17,1) -> 7166.6667 | Y8: =$E8/12*M8*IF(AND($J8=1,Y$5>=Assumptions!$B$18),1+Assumptions!$B$17,1) -> 7166.6667 | Z8: =$E8/12*N8*IF(AND($J8=1,Z$5>=Assumptions!$B$18),1+Assumptions!$B$17,1) -> 7417.5 | AA8: =$E8/12*O8*IF(AND($J8=1,AA$5>=Assumptions!$B$18),1+Assumptions!$B$17,1) -> 7417.5 | AB8: =$E8/12*P8*IF(AND($J8=1,AB$5>=Assumptions!$B$18),1+Assumptions!$B$17,1) -> 7417.5 | AC8: =$E8/12*Q8*IF(AND($J8=1,AC$5>=Assumptions!$B$18),1+Assumptions!$B$17,1) -> 7417.5 | AD8: =$E8/12*R8*IF(AND($J8=1,AD$5>=Assumptions!$B$18),1+Assumptions!$B$17,1) -> 7417.5 | ... AH8: =$E8/12*V8*IF(AND($J8=1,AH$5>=Assumptions!$B$18),1+Assumptions!$B$17,1) -> 7417.5
A9: =Roster!A9 -> ENG-104 | B9: =Roster!B9 -> Engineering | C9: =Roster!E9 -> Existing | D9: =Roster!D9 -> 1 | E9: =Roster!F9 -> 79500 | F9: =IF(Roster!E9="Open role",MAX(Assumptions!$B$14,EDATE(Roster!G9,IF(Roster!I9=2,Assumptions!$F$10,0)-Assumptions!$F$9)),Roster!G9) -> 45170 | G9: =IF(Roster!H9="",DATE(2099,12,31),Roster!H9) -> 73050 | H9: =IF(Roster!E9="Existing",1,IF(Roster!I9<=Assumptions!$F$8,1,0)) -> 1 | I9: =IF(B9="Sales",Assumptions!$B$23,VLOOKUP(D9,Assumptions!$A$27:$B$31,2,FALSE())) -> 0.05 | J9: =IF(F9<Assumptions!$B$14,1,0) -> 1 | K9: =IF($H9=1,MAX(0,MIN($G9,EOMONTH(K$5,0))-MAX($F9,K$5)+1)/DAY(EOMONTH(K$5,0)),0) -> 1 | L9: =IF($H9=1,MAX(0,MIN($G9,EOMONTH(L$5,0))-MAX($F9,L$5)+1)/DAY(EOMONTH(L$5,0)),0) -> 1 | M9: =IF($H9=1,MAX(0,MIN($G9,EOMONTH(M$5,0))-MAX($F9,M$5)+1)/DAY(EOMONTH(M$5,0)),0) -> 1 | N9: =IF($H9=1,MAX(0,MIN($G9,EOMONTH(N$5,0))-MAX($F9,N$5)+1)/DAY(EOMONTH(N$5,0)),0) -> 1 | O9: =IF($H9=1,MAX(0,MIN($G9,EOMONTH(O$5,0))-MAX($F9,O$5)+1)/DAY(EOMONTH(O$5,0)),0) -> 1 | P9: =IF($H9=1,MAX(0,MIN($G9,EOMONTH(P$5,0))-MAX($F9,P$5)+1)/DAY(EOMONTH(P$5,0)),0) -> 1 | Q9: =IF($H9=1,MAX(0,MIN($G9,EOMONTH(Q$5,0))-MAX($F9,Q$5)+1)/DAY(EOMONTH(Q$5,0)),0) -> 1 | R9: =IF($H9=1,MAX(0,MIN($G9,EOMONTH(R$5,0))-MAX($F9,R$5)+1)/DAY(EOMONTH(R$5,0)),0) -> 1 | ... V9: =IF($H9=1,MAX(0,MIN($G9,EOMONTH(V$5,0))-MAX($F9,V$5)+1)/DAY(EOMONTH(V$5,0)),0) -> 1 | W9: =$E9/12*K9*IF(AND($J9=1,W$5>=Assumptions!$B$18),1+Assumptions!$B$17,1) -> 6625 | X9: =$E9/12*L9*IF(AND($J9=1,X$5>=Assumptions!$B$18),1+Assumptions!$B$17,1) -> 6625 | Y9: =$E9/12*M9*IF(AND($J9=1,Y$5>=Assumptions!$B$18),1+Assumptions!$B$17,1) -> 6625 | Z9: =$E9/12*N9*IF(AND($J9=1,Z$5>=Assumptions!$B$18),1+Assumptions!$B$17,1) -> 6856.875 | AA9: =$E9/12*O9*IF(AND($J9=1,AA$5>=Assumptions!$B$18),1+Assumptions!$B$17,1) -> 6856.875 | AB9: =$E9/12*P9*IF(AND($J9=1,AB$5>=Assumptions!$B$18),1+Assumptions!$B$17,1) -> 6856.875 | AC9: =$E9/12*Q9*IF(AND($J9=1,AC$5>=Assumptions!$B$18),1+Assumptions!$B$17,1) -> 6856.875 | AD9: =$E9/12*R9*IF(AND($J9=1,AD$5>=Assumptions!$B$18),1+Assumptions!$B$17,1) -> 6856.875 | ... AH9: =$E9/12*V9*IF(AND($J9=1,AH$5>=Assumptions!$B$18),1+Assumptions!$B$17,1) -> 6856.875
A10: =Roster!A10 -> ENG-105 | B10: =Roster!B10 -> Engineering | C10: =Roster!E10 -> Existing | D10: =Roster!D10 -> 2 | E10: =Roster!F10 -> 110500 | F10: =IF(Roster!E10="Open role",MAX(Assumptions!$B$14,EDATE(Roster!G10,IF(Roster!I10=2,Assumptions!$F$10,0)-Assumptions!$F$9)),Roster!G10) -> 46054 | G10: =IF(Roster!H10="",DATE(2099,12,31),Roster!H10) -> 73050 | H10: =IF(Roster!E10="Existing",1,IF(Roster!I10<=Assumptions!$F$8,1,0)) -> 1 | I10: =IF(B10="Sales",Assumptions!$B$23,VLOOKUP(D10,Assumptions!$A$27:$B$31,2,FALSE())) -> 0.08 | J10: =IF(F10<Assumptions!$B$14,1,0) -> 1 | K10: =IF($H10=1,MAX(0,MIN($G10,EOMONTH(K$5,0))-MAX($F10,K$5)+1)/DAY(EOMONTH(K$5,0)),0) -> 1 | L10: =IF($H10=1,MAX(0,MIN($G10,EOMONTH(L$5,0))-MAX($F10,L$5)+1)/DAY(EOMONTH(L$5,0)),0) -> 1 | M10: =IF($H10=1,MAX(0,MIN($G10,EOMONTH(M$5,0))-MAX($F10,M$5)+1)/DAY(EOMONTH(M$5,0)),0) -> 1 | N10: =IF($H10=1,MAX(0,MIN($G10,EOMONTH(N$5,0))-MAX($F10,N$5)+1)/DAY(EOMONTH(N$5,0)),0) -> 1 | O10: =IF($H10=1,MAX(0,MIN($G10,EOMONTH(O$5,0))-MAX($F10,O$5)+1)/DAY(EOMONTH(O$5,0)),0) -> 1 | P10: =IF($H10=1,MAX(0,MIN($G10,EOMONTH(P$5,0))-MAX($F10,P$5)+1)/DAY(EOMONTH(P$5,0)),0) -> 1 | Q10: =IF($H10=1,MAX(0,MIN($G10,EOMONTH(Q$5,0))-MAX($F10,Q$5)+1)/DAY(EOMONTH(Q$5,0)),0) -> 1 | R10: =IF($H10=1,MAX(0,MIN($G10,EOMONTH(R$5,0))-MAX($F10,R$5)+1)/DAY(EOMONTH(R$5,0)),0) -> 1 | ... V10: =IF($H10=1,MAX(0,MIN($G10,EOMONTH(V$5,0))-MAX($F10,V$5)+1)/DAY(EOMONTH(V$5,0)),0) -> 1 | W10: =$E10/12*K10*IF(AND($J10=1,W$5>=Assumptions!$B$18),1+Assumptions!$B$17,1) -> 9208.3333 | X10: =$E10/12*L10*IF(AND($J10=1,X$5>=Assumptions!$B$18),1+Assumptions!$B$17,1) -> 9208.3333 | Y10: =$E10/12*M10*IF(AND($J10=1,Y$5>=Assumptions!$B$18),1+Assumptions!$B$17,1) -> 9208.3333 | Z10: =$E10/12*N10*IF(AND($J10=1,Z$5>=Assumptions!$B$18),1+Assumptions!$B$17,1) -> 9530.625 | AA10: =$E10/12*O10*IF(AND($J10=1,AA$5>=Assumptions!$B$18),1+Assumptions!$B$17,1) -> 9530.625 | AB10: =$E10/12*P10*IF(AND($J10=1,AB$5>=Assumptions!$B$18),1+Assumptions!$B$17,1) -> 9530.625 | AC10: =$E10/12*Q10*IF(AND($J10=1,AC$5>=Assumptions!$B$18),1+Assumptions!$B$17,1) -> 9530.625 | AD10: =$E10/12*R10*IF(AND($J10=1,AD$5>=Assumptions!$B$18),1+Assumptions!$B$17,1) -> 9530.625 | ... AH10: =$E10/12*V10*IF(AND($J10=1,AH$5>=Assumptions!$B$18),1+Assumptions!$B$17,1) -> 9530.625
A11: =Roster!A11 -> ENG-106 | B11: =Roster!B11 -> Engineering | C11: =Roster!E11 -> Existing | D11: =Roster!D11 -> 2 | E11: =Roster!F11 -> 108000 | F11: =IF(Roster!E11="Open role",MAX(Assumptions!$B$14,EDATE(Roster!G11,IF(Roster!I11=2,Assumptions!$F$10,0)-Assumptions!$F$9)),Roster!G11) -> 44378 | G11: =IF(Roster!H11="",DATE(2099,12,31),Roster!H11) -> 73050 | H11: =IF(Roster!E11="Existing",1,IF(Roster!I11<=Assumptions!$F$8,1,0)) -> 1 | I11: =IF(B11="Sales",Assumptions!$B$23,VLOOKUP(D11,Assumptions!$A$27:$B$31,2,FALSE())) -> 0.08 | J11: =IF(F11<Assumptions!$B$14,1,0) -> 1 | K11: =IF($H11=1,MAX(0,MIN($G11,EOMONTH(K$5,0))-MAX($F11,K$5)+1)/DAY(EOMONTH(K$5,0)),0) -> 1 | L11: =IF($H11=1,MAX(0,MIN($G11,EOMONTH(L$5,0))-MAX($F11,L$5)+1)/DAY(EOMONTH(L$5,0)),0) -> 1 | M11: =IF($H11=1,MAX(0,MIN($G11,EOMONTH(M$5,0))-MAX($F11,M$5)+1)/DAY(EOMONTH(M$5,0)),0) -> 1 | N11: =IF($H11=1,MAX(0,MIN($G11,EOMONTH(N$5,0))-MAX($F11,N$5)+1)/DAY(EOMONTH(N$5,0)),0) -> 1 | O11: =IF($H11=1,MAX(0,MIN($G11,EOMONTH(O$5,0))-MAX($F11,O$5)+1)/DAY(EOMONTH(O$5,0)),0) -> 1 | P11: =IF($H11=1,MAX(0,MIN($G11,EOMONTH(P$5,0))-MAX($F11,P$5)+1)/DAY(EOMONTH(P$5,0)),0) -> 1 | Q11: =IF($H11=1,MAX(0,MIN($G11,EOMONTH(Q$5,0))-MAX($F11,Q$5)+1)/DAY(EOMONTH(Q$5,0)),0) -> 1 | R11: =IF($H11=1,MAX(0,MIN($G11,EOMONTH(R$5,0))-MAX($F11,R$5)+1)/DAY(EOMONTH(R$5,0)),0) -> 1 | ... V11: =IF($H11=1,MAX(0,MIN($G11,EOMONTH(V$5,0))-MAX($F11,V$5)+1)/DAY(EOMONTH(V$5,0)),0) -> 1 | W11: =$E11/12*K11*IF(AND($J11=1,W$5>=Assumptions!$B$18),1+Assumptions!$B$17,1) -> 9000 | X11: =$E11/12*L11*IF(AND($J11=1,X$5>=Assumptions!$B$18),1+Assumptions!$B$17,1) -> 9000 | Y11: =$E11/12*M11*IF(AND($J11=1,Y$5>=Assumptions!$B$18),1+Assumptions!$B$17,1) -> 9000 | Z11: =$E11/12*N11*IF(AND($J11=1,Z$5>=Assumptions!$B$18),1+Assumptions!$B$17,1) -> 9315 | AA11: =$E11/12*O11*IF(AND($J11=1,AA$5>=Assumptions!$B$18),1+Assumptions!$B$17,1) -> 9315 | AB11: =$E11/12*P11*IF(AND($J11=1,AB$5>=Assumptions!$B$18),1+Assumptions!$B$17,1) -> 9315 | AC11: =$E11/12*Q11*IF(AND($J11=1,AC$5>=Assumptions!$B$18),1+Assumptions!$B$17,1) -> 9315 | AD11: =$E11/12*R11*IF(AND($J11=1,AD$5>=Assumptions!$B$18),1+Assumptions!$B$17,1) -> 9315 | ... AH11: =$E11/12*V11*IF(AND($J11=1,AH$5>=Assumptions!$B$18),1+Assumptions!$B$17,1) -> 9315
A12: =Roster!A12 -> ENG-107 | B12: =Roster!B12 -> Engineering | C12: =Roster!E12 -> Existing | D12: =Roster!D12 -> 2 | E12: =Roster!F12 -> 112500 | F12: =IF(Roster!E12="Open role",MAX(Assumptions!$B$14,EDATE(Roster!G12,IF(Roster!I12=2,Assumptions!$F$10,0)-Assumptions!$F$9)),Roster!G12) -> 45627 | G12: =IF(Roster!H12="",DATE(2099,12,31),Roster!H12) -> 73050 | H12: =IF(Roster!E12="Existing",1,IF(Roster!I12<=Assumptions!$F$8,1,0)) -> 1 | I12: =IF(B12="Sales",Assumptions!$B$23,VLOOKUP(D12,Assumptions!$A$27:$B$31,2,FALSE())) -> 0.08 | J12: =IF(F12<Assumptions!$B$14,1,0) -> 1 | K12: =IF($H12=1,MAX(0,MIN($G12,EOMONTH(K$5,0))-MAX($F12,K$5)+1)/DAY(EOMONTH(K$5,0)),0) -> 1 | L12: =IF($H12=1,MAX(0,MIN($G12,EOMONTH(L$5,0))-MAX($F12,L$5)+1)/DAY(EOMONTH(L$5,0)),0) -> 1 | M12: =IF($H12=1,MAX(0,MIN($G12,EOMONTH(M$5,0))-MAX($F12,M$5)+1)/DAY(EOMONTH(M$5,0)),0) -> 1 | N12: =IF($H12=1,MAX(0,MIN($G12,EOMONTH(N$5,0))-MAX($F12,N$5)+1)/DAY(EOMONTH(N$5,0)),0) -> 1 | O12: =IF($H12=1,MAX(0,MIN($G12,EOMONTH(O$5,0))-MAX($F12,O$5)+1)/DAY(EOMONTH(O$5,0)),0) -> 1 | P12: =IF($H12=1,MAX(0,MIN($G12,EOMONTH(P$5,0))-MAX($F12,P$5)+1)/DAY(EOMONTH(P$5,0)),0) -> 1 | Q12: =IF($H12=1,MAX(0,MIN($G12,EOMONTH(Q$5,0))-MAX($F12,Q$5)+1)/DAY(EOMONTH(Q$5,0)),0) -> 1 | R12: =IF($H12=1,MAX(0,MIN($G12,EOMONTH(R$5,0))-MAX($F12,R$5)+1)/DAY(EOMONTH(R$5,0)),0) -> 1 | ... V12: =IF($H12=1,MAX(0,MIN($G12,EOMONTH(V$5,0))-MAX($F12,V$5)+1)/DAY(EOMONTH(V$5,0)),0) -> 1 | W12: =$E12/12*K12*IF(AND($J12=1,W$5>=Assumptions!$B$18),1+Assumptions!$B$17,1) -> 9375 | X12: =$E12/12*L12*IF(AND($J12=1,X$5>=Assumptions!$B$18),1+Assumptions!$B$17,1) -> 9375 | Y12: =$E12/12*M12*IF(AND($J12=1,Y$5>=Assumptions!$B$18),1+Assumptions!$B$17,1) -> 9375 | Z12: =$E12/12*N12*IF(AND($J12=1,Z$5>=Assumptions!$B$18),1+Assumptions!$B$17,1) -> 9703.125 | AA12: =$E12/12*O12*IF(AND($J12=1,AA$5>=Assumptions!$B$18),1+Assumptions!$B$17,1) -> 9703.125 | AB12: =$E12/12*P12*IF(AND($J12=1,AB$5>=Assumptions!$B$18),1+Assumptions!$B$17,1) -> 9703.125 | AC12: =$E12/12*Q12*IF(AND($J12=1,AC$5>=Assumptions!$B$18),1+Assumptions!$B$17,1) -> 9703.125 | AD12: =$E12/12*R12*IF(AND($J12=1,AD$5>=Assumptions!$B$18),1+Assumptions!$B$17,1) -> 9703.125 | ... AH12: =$E12/12*V12*IF(AND($J12=1,AH$5>=Assumptions!$B$18),1+Assumptions!$B$17,1) -> 9703.125
A13: =Roster!A13 -> ENG-108 | B13: =Roster!B13 -> Engineering | C13: =Roster!E13 -> Existing | D13: =Roster!D13 -> 2 | E13: =Roster!F13 -> 109000 | F13: =IF(Roster!E13="Open role",MAX(Assumptions!$B$14,EDATE(Roster!G13,IF(Roster!I13=2,Assumptions!$F$10,0)-Assumptions!$F$9)),Roster!G13) -> 43586 | G13: =IF(Roster!H13="",DATE(2099,12,31),Roster!H13) -> 73050 | H13: =IF(Roster!E13="Existing",1,IF(Roster!I13<=Assumptions!$F$8,1,0)) -> 1 | I13: =IF(B13="Sales",Assumptions!$B$23,VLOOKUP(D13,Assumptions!$A$27:$B$31,2,FALSE())) -> 0.08 | J13: =IF(F13<Assumptions!$B$14,1,0) -> 1 | K13: =IF($H13=1,MAX(0,MIN($G13,EOMONTH(K$5,0))-MAX($F13,K$5)+1)/DAY(EOMONTH(K$5,0)),0) -> 1 | L13: =IF($H13=1,MAX(0,MIN($G13,EOMONTH(L$5,0))-MAX($F13,L$5)+1)/DAY(EOMONTH(L$5,0)),0) -> 1 | M13: =IF($H13=1,MAX(0,MIN($G13,EOMONTH(M$5,0))-MAX($F13,M$5)+1)/DAY(EOMONTH(M$5,0)),0) -> 1 | N13: =IF($H13=1,MAX(0,MIN($G13,EOMONTH(N$5,0))-MAX($F13,N$5)+1)/DAY(EOMONTH(N$5,0)),0) -> 1 | O13: =IF($H13=1,MAX(0,MIN($G13,EOMONTH(O$5,0))-MAX($F13,O$5)+1)/DAY(EOMONTH(O$5,0)),0) -> 1 | P13: =IF($H13=1,MAX(0,MIN($G13,EOMONTH(P$5,0))-MAX($F13,P$5)+1)/DAY(EOMONTH(P$5,0)),0) -> 1 | Q13: =IF($H13=1,MAX(0,MIN($G13,EOMONTH(Q$5,0))-MAX($F13,Q$5)+1)/DAY(EOMONTH(Q$5,0)),0) -> 1 | R13: =IF($H13=1,MAX(0,MIN($G13,EOMONTH(R$5,0))-MAX($F13,R$5)+1)/DAY(EOMONTH(R$5,0)),0) -> 1 | ... V13: =IF($H13=1,MAX(0,MIN($G13,EOMONTH(V$5,0))-MAX($F13,V$5)+1)/DAY(EOMONTH(V$5,0)),0) -> 1 | W13: =$E13/12*K13*IF(AND($J13=1,W$5>=Assumptions!$B$18),1+Assumptions!$B$17,1) -> 9083.3333 | X13: =$E13/12*L13*IF(AND($J13=1,X$5>=Assumptions!$B$18),1+Assumptions!$B$17,1) -> 9083.3333 | Y13: =$E13/12*M13*IF(AND($J13=1,Y$5>=Assumptions!$B$18),1+Assumptions!$B$17,1) -> 9083.3333 | Z13: =$E13/12*N13*IF(AND($J13=1,Z$5>=Assumptions!$B$18),1+Assumptions!$B$17,1) -> 9401.25 | AA13: =$E13/12*O13*IF(AND($J13=1,AA$5>=Assumptions!$B$18),1+Assumptions!$B$17,1) -> 9401.25 | AB13: =$E13/12*P13*IF(AND($J13=1,AB$5>=Assumptions!$B$18),1+Assumptions!$B$17,1) -> 9401.25 | AC13: =$E13/12*Q13*IF(AND($J13=1,AC$5>=Assumptions!$B$18),1+Assumptions!$B$17,1) -> 9401.25 | AD13: =$E13/12*R13*IF(AND($J13=1,AD$5>=Assumptions!$B$18),1+Assumptions!$B$17,1) -> 9401.25 | ... AH13: =$E13/12*V13*IF(AND($J13=1,AH$5>=Assumptions!$B$18),1+Assumptions!$B$17,1) -> 9401.25
A14: =Roster!A14 -> ENG-109 | B14: =Roster!B14 -> Engineering | C14: =Roster!E14 -> Existing | D14: =Roster!D14 -> 2 | E14: =Roster!F14 -> 111500 | F14: =IF(Roster!E14="Open role",MAX(Assumptions!$B$14,EDATE(Roster!G14,IF(Roster!I14=2,Assumptions!$F$10,0)-Assumptions!$F$9)),Roster!G14) -> 44835 | G14: =IF(Roster!H14="",DATE(2099,12,31),Roster!H14) -> 73050 | H14: =IF(Roster!E14="Existing",1,IF(Roster!I14<=Assumptions!$F$8,1,0)) -> 1 | I14: =IF(B14="Sales",Assumptions!$B$23,VLOOKUP(D14,Assumptions!$A$27:$B$31,2,FALSE())) -> 0.08 | J14: =IF(F14<Assumptions!$B$14,1,0) -> 1 | K14: =IF($H14=1,MAX(0,MIN($G14,EOMONTH(K$5,0))-MAX($F14,K$5)+1)/DAY(EOMONTH(K$5,0)),0) -> 1 | L14: =IF($H14=1,MAX(0,MIN($G14,EOMONTH(L$5,0))-MAX($F14,L$5)+1)/DAY(EOMONTH(L$5,0)),0) -> 1 | M14: =IF($H14=1,MAX(0,MIN($G14,EOMONTH(M$5,0))-MAX($F14,M$5)+1)/DAY(EOMONTH(M$5,0)),0) -> 1 | N14: =IF($H14=1,MAX(0,MIN($G14,EOMONTH(N$5,0))-MAX($F14,N$5)+1)/DAY(EOMONTH(N$5,0)),0) -> 1 | O14: =IF($H14=1,MAX(0,MIN($G14,EOMONTH(O$5,0))-MAX($F14,O$5)+1)/DAY(EOMONTH(O$5,0)),0) -> 1 | P14: =IF($H14=1,MAX(0,MIN($G14,EOMONTH(P$5,0))-MAX($F14,P$5)+1)/DAY(EOMONTH(P$5,0)),0) -> 1 | Q14: =IF($H14=1,MAX(0,MIN($G14,EOMONTH(Q$5,0))-MAX($F14,Q$5)+1)/DAY(EOMONTH(Q$5,0)),0) -> 1 | R14: =IF($H14=1,MAX(0,MIN($G14,EOMONTH(R$5,0))-MAX($F14,R$5)+1)/DAY(EOMONTH(R$5,0)),0) -> 1 | ... V14: =IF($H14=1,MAX(0,MIN($G14,EOMONTH(V$5,0))-MAX($F14,V$5)+1)/DAY(EOMONTH(V$5,0)),0) -> 1 | W14: =$E14/12*K14*IF(AND($J14=1,W$5>=Assumptions!$B$18),1+Assumptions!$B$17,1) -> 9291.6667 | X14: =$E14/12*L14*IF(AND($J14=1,X$5>=Assumptions!$B$18),1+Assumptions!$B$17,1) -> 9291.6667 | Y14: =$E14/12*M14*IF(AND($J14=1,Y$5>=Assumptions!$B$18),1+Assumptions!$B$17,1) -> 9291.6667 | Z14: =$E14/12*N14*IF(AND($J14=1,Z$5>=Assumptions!$B$18),1+Assumptions!$B$17,1) -> 9616.875 | AA14: =$E14/12*O14*IF(AND($J14=1,AA$5>=Assumptions!$B$18),1+Assumptions!$B$17,1) -> 9616.875 | AB14: =$E14/12*P14*IF(AND($J14=1,AB$5>=Assumptions!$B$18),1+Assumptions!$B$17,1) -> 9616.875 | AC14: =$E14/12*Q14*IF(AND($J14=1,AC$5>=Assumptions!$B$18),1+Assumptions!$B$17,1) -> 9616.875 | AD14: =$E14/12*R14*IF(AND($J14=1,AD$5>=Assumptions!$B$18),1+Assumptions!$B$17,1) -> 9616.875 | ... AH14: =$E14/12*V14*IF(AND($J14=1,AH$5>=Assumptions!$B$18),1+Assumptions!$B$17,1) -> 9616.875
A15: =Roster!A15 -> ENG-110 | B15: =Roster!B15 -> Engineering | C15: =Roster!E15 -> Existing | D15: =Roster!D15 -> 2 | E15: =Roster!F15 -> 107000 | F15: =IF(Roster!E15="Open role",MAX(Assumptions!$B$14,EDATE(Roster!G15,IF(Roster!I15=2,Assumptions!$F$10,0)-Assumptions!$F$9)),Roster!G15) -> 45717 | G15: =IF(Roster!H15="",DATE(2099,12,31),Roster!H15) -> 73050 | H15: =IF(Roster!E15="Existing",1,IF(Roster!I15<=Assumptions!$F$8,1,0)) -> 1 | I15: =IF(B15="Sales",Assumptions!$B$23,VLOOKUP(D15,Assumptions!$A$27:$B$31,2,FALSE())) -> 0.08 | J15: =IF(F15<Assumptions!$B$14,1,0) -> 1 | K15: =IF($H15=1,MAX(0,MIN($G15,EOMONTH(K$5,0))-MAX($F15,K$5)+1)/DAY(EOMONTH(K$5,0)),0) -> 1 | L15: =IF($H15=1,MAX(0,MIN($G15,EOMONTH(L$5,0))-MAX($F15,L$5)+1)/DAY(EOMONTH(L$5,0)),0) -> 1 | M15: =IF($H15=1,MAX(0,MIN($G15,EOMONTH(M$5,0))-MAX($F15,M$5)+1)/DAY(EOMONTH(M$5,0)),0) -> 1 | N15: =IF($H15=1,MAX(0,MIN($G15,EOMONTH(N$5,0))-MAX($F15,N$5)+1)/DAY(EOMONTH(N$5,0)),0) -> 1 | O15: =IF($H15=1,MAX(0,MIN($G15,EOMONTH(O$5,0))-MAX($F15,O$5)+1)/DAY(EOMONTH(O$5,0)),0) -> 1 | P15: =IF($H15=1,MAX(0,MIN($G15,EOMONTH(P$5,0))-MAX($F15,P$5)+1)/DAY(EOMONTH(P$5,0)),0) -> 1 | Q15: =IF($H15=1,MAX(0,MIN($G15,EOMONTH(Q$5,0))-MAX($F15,Q$5)+1)/DAY(EOMONTH(Q$5,0)),0) -> 1 | R15: =IF($H15=1,MAX(0,MIN($G15,EOMONTH(R$5,0))-MAX($F15,R$5)+1)/DAY(EOMONTH(R$5,0)),0) -> 1 | ... V15: =IF($H15=1,MAX(0,MIN($G15,EOMONTH(V$5,0))-MAX($F15,V$5)+1)/DAY(EOMONTH(V$5,0)),0) -> 1 | W15: =$E15/12*K15*IF(AND($J15=1,W$5>=Assumptions!$B$18),1+Assumptions!$B$17,1) -> 8916.6667 | X15: =$E15/12*L15*IF(AND($J15=1,X$5>=Assumptions!$B$18),1+Assumptions!$B$17,1) -> 8916.6667 | Y15: =$E15/12*M15*IF(AND($J15=1,Y$5>=Assumptions!$B$18),1+Assumptions!$B$17,1) -> 8916.6667 | Z15: =$E15/12*N15*IF(AND($J15=1,Z$5>=Assumptions!$B$18),1+Assumptions!$B$17,1) -> 9228.75 | AA15: =$E15/12*O15*IF(AND($J15=1,AA$5>=Assumptions!$B$18),1+Assumptions!$B$17,1) -> 9228.75 | AB15: =$E15/12*P15*IF(AND($J15=1,AB$5>=Assumptions!$B$18),1+Assumptions!$B$17,1) -> 9228.75 | AC15: =$E15/12*Q15*IF(AND($J15=1,AC$5>=Assumptions!$B$18),1+Assumptions!$B$17,1) -> 9228.75 | AD15: =$E15/12*R15*IF(AND($J15=1,AD$5>=Assumptions!$B$18),1+Assumptions!$B$17,1) -> 9228.75 | ... AH15: =$E15/12*V15*IF(AND($J15=1,AH$5>=Assumptions!$B$18),1+Assumptions!$B$17,1) -> 9228.75
A16: =Roster!A16 -> ENG-111 | B16: =Roster!B16 -> Engineering | C16: =Roster!E16 -> Existing | D16: =Roster!D16 -> 3 | E16: =Roster!F16 -> 153000 | F16: =IF(Roster!E16="Open role",MAX(Assumptions!$B$14,EDATE(Roster!G16,IF(Roster!I16=2,Assumptions!$F$10,0)-Assumptions!$F$9)),Roster!G16) -> 44044 | G16: =IF(Roster!H16="",DATE(2099,12,31),Roster!H16) -> 46507 | H16: =IF(Roster!E16="Existing",1,IF(Roster!I16<=Assumptions!$F$8,1,0)) -> 1 | I16: =IF(B16="Sales",Assumptions!$B$23,VLOOKUP(D16,Assumptions!$A$27:$B$31,2,FALSE())) -> 0.1 | J16: =IF(F16<Assumptions!$B$14,1,0) -> 1 | K16: =IF($H16=1,MAX(0,MIN($G16,EOMONTH(K$5,0))-MAX($F16,K$5)+1)/DAY(EOMONTH(K$5,0)),0) -> 1 | L16: =IF($H16=1,MAX(0,MIN($G16,EOMONTH(L$5,0))-MAX($F16,L$5)+1)/DAY(EOMONTH(L$5,0)),0) -> 1 | M16: =IF($H16=1,MAX(0,MIN($G16,EOMONTH(M$5,0))-MAX($F16,M$5)+1)/DAY(EOMONTH(M$5,0)),0) -> 1 | N16: =IF($H16=1,MAX(0,MIN($G16,EOMONTH(N$5,0))-MAX($F16,N$5)+1)/DAY(EOMONTH(N$5,0)),0) -> 1 | O16: =IF($H16=1,MAX(0,MIN($G16,EOMONTH(O$5,0))-MAX($F16,O$5)+1)/DAY(EOMONTH(O$5,0)),0) -> 0 | P16: =IF($H16=1,MAX(0,MIN($G16,EOMONTH(P$5,0))-MAX($F16,P$5)+1)/DAY(EOMONTH(P$5,0)),0) -> 0 | Q16: =IF($H16=1,MAX(0,MIN($G16,EOMONTH(Q$5,0))-MAX($F16,Q$5)+1)/DAY(EOMONTH(Q$5,0)),0) -> 0 | R16: =IF($H16=1,MAX(0,MIN($G16,EOMONTH(R$5,0))-MAX($F16,R$5)+1)/DAY(EOMONTH(R$5,0)),0) -> 0 | ... V16: =IF($H16=1,MAX(0,MIN($G16,EOMONTH(V$5,0))-MAX($F16,V$5)+1)/DAY(EOMONTH(V$5,0)),0) -> 0 | W16: =$E16/12*K16*IF(AND($J16=1,W$5>=Assumptions!$B$18),1+Assumptions!$B$17,1) -> 12750 | X16: =$E16/12*L16*IF(AND($J16=1,X$5>=Assumptions!$B$18),1+Assumptions!$B$17,1) -> 12750 | Y16: =$E16/12*M16*IF(AND($J16=1,Y$5>=Assumptions!$B$18),1+Assumptions!$B$17,1) -> 12750 | Z16: =$E16/12*N16*IF(AND($J16=1,Z$5>=Assumptions!$B$18),1+Assumptions!$B$17,1) -> 13196.25 | AA16: =$E16/12*O16*IF(AND($J16=1,AA$5>=Assumptions!$B$18),1+Assumptions!$B$17,1) -> 0 | AB16: =$E16/12*P16*IF(AND($J16=1,AB$5>=Assumptions!$B$18),1+Assumptions!$B$17,1) -> 0 | AC16: =$E16/12*Q16*IF(AND($J16=1,AC$5>=Assumptions!$B$18),1+Assumptions!$B$17,1) -> 0 | AD16: =$E16/12*R16*IF(AND($J16=1,AD$5>=Assumptions!$B$18),1+Assumptions!$B$17,1) -> 0 | ... AH16: =$E16/12*V16*IF(AND($J16=1,AH$5>=Assumptions!$B$18),1+Assumptions!$B$17,1) -> 0
A17: =Roster!A17 -> ENG-112 | B17: =Roster!B17 -> Engineering | C17: =Roster!E17 -> Existing | D17: =Roster!D17 -> 3 | E17: =Roster!F17 -> 141500 | F17: =IF(Roster!E17="Open role",MAX(Assumptions!$B$14,EDATE(Roster!G17,IF(Roster!I17=2,Assumptions!$F$10,0)-Assumptions!$F$9)),Roster!G17) -> 44927 | G17: =IF(Roster!H17="",DATE(2099,12,31),Roster!H17) -> 73050 | H17: =IF(Roster!E17="Existing",1,IF(Roster!I17<=Assumptions!$F$8,1,0)) -> 1 | I17: =IF(B17="Sales",Assumptions!$B$23,VLOOKUP(D17,Assumptions!$A$27:$B$31,2,FALSE())) -> 0.1 | J17: =IF(F17<Assumptions!$B$14,1,0) -> 1 | K17: =IF($H17=1,MAX(0,MIN($G17,EOMONTH(K$5,0))-MAX($F17,K$5)+1)/DAY(EOMONTH(K$5,0)),0) -> 1 | L17: =IF($H17=1,MAX(0,MIN($G17,EOMONTH(L$5,0))-MAX($F17,L$5)+1)/DAY(EOMONTH(L$5,0)),0) -> 1 | M17: =IF($H17=1,MAX(0,MIN($G17,EOMONTH(M$5,0))-MAX($F17,M$5)+1)/DAY(EOMONTH(M$5,0)),0) -> 1 | N17: =IF($H17=1,MAX(0,MIN($G17,EOMONTH(N$5,0))-MAX($F17,N$5)+1)/DAY(EOMONTH(N$5,0)),0) -> 1 | O17: =IF($H17=1,MAX(0,MIN($G17,EOMONTH(O$5,0))-MAX($F17,O$5)+1)/DAY(EOMONTH(O$5,0)),0) -> 1 | P17: =IF($H17=1,MAX(0,MIN($G17,EOMONTH(P$5,0))-MAX($F17,P$5)+1)/DAY(EOMONTH(P$5,0)),0) -> 1 | Q17: =IF($H17=1,MAX(0,MIN($G17,EOMONTH(Q$5,0))-MAX($F17,Q$5)+1)/DAY(EOMONTH(Q$5,0)),0) -> 1 | R17: =IF($H17=1,MAX(0,MIN($G17,EOMONTH(R$5,0))-MAX($F17,R$5)+1)/DAY(EOMONTH(R$5,0)),0) -> 1 | ... V17: =IF($H17=1,MAX(0,MIN($G17,EOMONTH(V$5,0))-MAX($F17,V$5)+1)/DAY(EOMONTH(V$5,0)),0) -> 1 | W17: =$E17/12*K17*IF(AND($J17=1,W$5>=Assumptions!$B$18),1+Assumptions!$B$17,1) -> 11791.667 | X17: =$E17/12*L17*IF(AND($J17=1,X$5>=Assumptions!$B$18),1+Assumptions!$B$17,1) -> 11791.667 | Y17: =$E17/12*M17*IF(AND($J17=1,Y$5>=Assumptions!$B$18),1+Assumptions!$B$17,1) -> 11791.667 | Z17: =$E17/12*N17*IF(AND($J17=1,Z$5>=Assumptions!$B$18),1+Assumptions!$B$17,1) -> 12204.375 | AA17: =$E17/12*O17*IF(AND($J17=1,AA$5>=Assumptions!$B$18),1+Assumptions!$B$17,1) -> 12204.375 | AB17: =$E17/12*P17*IF(AND($J17=1,AB$5>=Assumptions!$B$18),1+Assumptions!$B$17,1) -> 12204.375 | AC17: =$E17/12*Q17*IF(AND($J17=1,AC$5>=Assumptions!$B$18),1+Assumptions!$B$17,1) -> 12204.375 | AD17: =$E17/12*R17*IF(AND($J17=1,AD$5>=Assumptions!$B$18),1+Assumptions!$B$17,1) -> 12204.375 | ... AH17: =$E17/12*V17*IF(AND($J17=1,AH$5>=Assumptions!$B$18),1+Assumptions!$B$17,1) -> 12204.375
... A83: =Roster!A83 -> TBH-GNA-02 | B83: =Roster!B83 -> G&A | C83: =Roster!E83 -> Open role | D83: =Roster!D83 -> 2 | E83: =Roster!F83 -> 93000 | F83: =IF(Roster!E83="Open role",MAX(Assumptions!$B$14,EDATE(Roster!G83,IF(Roster!I83=2,Assumptions!$F$10,0)-Assumptions!$F$9)),Roster!G83) -> 46539 | G83: =IF(Roster!H83="",DATE(2099,12,31),Roster!H83) -> 73050 | H83: =IF(Roster!E83="Existing",1,IF(Roster!I83<=Assumptions!$F$8,1,0)) -> 1 | I83: =IF(B83="Sales",Assumptions!$B$23,VLOOKUP(D83,Assumptions!$A$27:$B$31,2,FALSE())) -> 0.08 | J83: =IF(F83<Assumptions!$B$14,1,0) -> 0 | K83: =IF($H83=1,MAX(0,MIN($G83,EOMONTH(K$5,0))-MAX($F83,K$5)+1)/DAY(EOMONTH(K$5,0)),0) -> 0 | L83: =IF($H83=1,MAX(0,MIN($G83,EOMONTH(L$5,0))-MAX($F83,L$5)+1)/DAY(EOMONTH(L$5,0)),0) -> 0 | M83: =IF($H83=1,MAX(0,MIN($G83,EOMONTH(M$5,0))-MAX($F83,M$5)+1)/DAY(EOMONTH(M$5,0)),0) -> 0 | N83: =IF($H83=1,MAX(0,MIN($G83,EOMONTH(N$5,0))-MAX($F83,N$5)+1)/DAY(EOMONTH(N$5,0)),0) -> 0 | O83: =IF($H83=1,MAX(0,MIN($G83,EOMONTH(O$5,0))-MAX($F83,O$5)+1)/DAY(EOMONTH(O$5,0)),0) -> 0 | P83: =IF($H83=1,MAX(0,MIN($G83,EOMONTH(P$5,0))-MAX($F83,P$5)+1)/DAY(EOMONTH(P$5,0)),0) -> 1 | Q83: =IF($H83=1,MAX(0,MIN($G83,EOMONTH(Q$5,0))-MAX($F83,Q$5)+1)/DAY(EOMONTH(Q$5,0)),0) -> 1 | R83: =IF($H83=1,MAX(0,MIN($G83,EOMONTH(R$5,0))-MAX($F83,R$5)+1)/DAY(EOMONTH(R$5,0)),0) -> 1 | ... V83: =IF($H83=1,MAX(0,MIN($G83,EOMONTH(V$5,0))-MAX($F83,V$5)+1)/DAY(EOMONTH(V$5,0)),0) -> 1 | W83: =$E83/12*K83*IF(AND($J83=1,W$5>=Assumptions!$B$18),1+Assumptions!$B$17,1) -> 0 | X83: =$E83/12*L83*IF(AND($J83=1,X$5>=Assumptions!$B$18),1+Assumptions!$B$17,1) -> 0 | Y83: =$E83/12*M83*IF(AND($J83=1,Y$5>=Assumptions!$B$18),1+Assumptions!$B$17,1) -> 0 | Z83: =$E83/12*N83*IF(AND($J83=1,Z$5>=Assumptions!$B$18),1+Assumptions!$B$17,1) -> 0 | AA83: =$E83/12*O83*IF(AND($J83=1,AA$5>=Assumptions!$B$18),1+Assumptions!$B$17,1) -> 0 | AB83: =$E83/12*P83*IF(AND($J83=1,AB$5>=Assumptions!$B$18),1+Assumptions!$B$17,1) -> 7750 | AC83: =$E83/12*Q83*IF(AND($J83=1,AC$5>=Assumptions!$B$18),1+Assumptions!$B$17,1) -> 7750 | AD83: =$E83/12*R83*IF(AND($J83=1,AD$5>=Assumptions!$B$18),1+Assumptions!$B$17,1) -> 7750 | ... AH83: =$E83/12*V83*IF(AND($J83=1,AH$5>=Assumptions!$B$18),1+Assumptions!$B$17,1) -> 7750
A84: Total | K84: =SUM(K6:K83) -> 60 | L84: =SUM(L6:L83) -> 62 | M84: =SUM(M6:M83) -> 64 | N84: =SUM(N6:N83) -> 66 | O84: =SUM(O6:O83) -> 67 | P84: =SUM(P6:P83) -> 70 | Q84: =SUM(Q6:Q83) -> 71 | R84: =SUM(R6:R83) -> 71 | ... AH84: =SUM(AH6:AH83) -> 697945.83

Sheet Department Budget
A1: FY2027 Operating Expense Budget by Department ($)
A2: ="Scenario: "&Assumptions!$C$5&" | Monthly budget, January–December 2027" -> Scenario: Plan | Monthly budget, January–December 2027
A4: Line item | B4: ='Headcount Calc'!K5 -> 46388 | C4: ='Headcount Calc'!L5 -> 46419 | D4: ='Headcount Calc'!M5 -> 46447 | E4: ='Headcount Calc'!N5 -> 46478 | F4: ='Headcount Calc'!O5 -> 46508 | G4: ='Headcount Calc'!P5 -> 46539 | H4: ='Headcount Calc'!Q5 -> 46569 | I4: ='Headcount Calc'!R5 -> 46600 | ... M4: ='Headcount Calc'!V5 -> 46722 | N4: FY2027
A6: Engineering
A7: FTE (average for the month) | B7: =SUMIF('Headcount Calc'!$B$6:$B$83,$A$6,'Headcount Calc'!K$6:K$83) -> 20 | C7: =SUMIF('Headcount Calc'!$B$6:$B$83,$A$6,'Headcount Calc'!L$6:L$83) -> 21 | D7: =SUMIF('Headcount Calc'!$B$6:$B$83,$A$6,'Headcount Calc'!M$6:M$83) -> 21 | E7: =SUMIF('Headcount Calc'!$B$6:$B$83,$A$6,'Headcount Calc'!N$6:N$83) -> 22 | F7: =SUMIF('Headcount Calc'!$B$6:$B$83,$A$6,'Headcount Calc'!O$6:O$83) -> 22 | G7: =SUMIF('Headcount Calc'!$B$6:$B$83,$A$6,'Headcount Calc'!P$6:P$83) -> 23 | H7: =SUMIF('Headcount Calc'!$B$6:$B$83,$A$6,'Headcount Calc'!Q$6:Q$83) -> 24 | I7: =SUMIF('Headcount Calc'!$B$6:$B$83,$A$6,'Headcount Calc'!R$6:R$83) -> 24 | ... M7: =SUMIF('Headcount Calc'!$B$6:$B$83,$A$6,'Headcount Calc'!V$6:V$83) -> 24 | N7: =AVERAGE(B7:M7) -> 22.75
A8: Salaries | B8: =SUMIF('Headcount Calc'!$B$6:$B$83,$A$6,'Headcount Calc'!W$6:W$83) -> 224708.33 | C8: =SUMIF('Headcount Calc'!$B$6:$B$83,$A$6,'Headcount Calc'!X$6:X$83) -> 233708.33 | D8: =SUMIF('Headcount Calc'!$B$6:$B$83,$A$6,'Headcount Calc'!Y$6:Y$83) -> 233708.33 | E8: =SUMIF('Headcount Calc'!$B$6:$B$83,$A$6,'Headcount Calc'!Z$6:Z$83) -> 250656.46 | F8: =SUMIF('Headcount Calc'!$B$6:$B$83,$A$6,'Headcount Calc'!AA$6:AA$83) -> 250085.21 | G8: =SUMIF('Headcount Calc'!$B$6:$B$83,$A$6,'Headcount Calc'!AB$6:AB$83) -> 262585.21 | H8: =SUMIF('Headcount Calc'!$B$6:$B$83,$A$6,'Headcount Calc'!AC$6:AC$83) -> 278085.21 | I8: =SUMIF('Headcount Calc'!$B$6:$B$83,$A$6,'Headcount Calc'!AD$6:AD$83) -> 278085.21 | ... M8: =SUMIF('Headcount Calc'!$B$6:$B$83,$A$6,'Headcount Calc'!AH$6:AH$83) -> 278085.21 | N8: =SUM(B8:M8) -> 3123963.1
A9: Bonus & variable compensation | B9: =SUMPRODUCT(('Headcount Calc'!$B$6:$B$83=$A$6)*'Headcount Calc'!W$6:W$83*'Headcount Calc'!$I$6:$I$83) -> 24423.333 | C9: =SUMPRODUCT(('Headcount Calc'!$B$6:$B$83=$A$6)*'Headcount Calc'!X$6:X$83*'Headcount Calc'!$I$6:$I$83) -> 25143.333 | D9: =SUMPRODUCT(('Headcount Calc'!$B$6:$B$83=$A$6)*'Headcount Calc'!Y$6:Y$83*'Headcount Calc'!$I$6:$I$83) -> 25143.333 | E9: =SUMPRODUCT(('Headcount Calc'!$B$6:$B$83=$A$6)*'Headcount Calc'!Z$6:Z$83*'Headcount Calc'!$I$6:$I$83) -> 26724.817 | F9: =SUMPRODUCT(('Headcount Calc'!$B$6:$B$83=$A$6)*'Headcount Calc'!AA$6:AA$83*'Headcount Calc'!$I$6:$I$83) -> 26667.692 | G9: =SUMPRODUCT(('Headcount Calc'!$B$6:$B$83=$A$6)*'Headcount Calc'!AB$6:AB$83*'Headcount Calc'!$I$6:$I$83) -> 27917.692 | H9: =SUMPRODUCT(('Headcount Calc'!$B$6:$B$83=$A$6)*'Headcount Calc'!AC$6:AC$83*'Headcount Calc'!$I$6:$I$83) -> 30242.692 | I9: =SUMPRODUCT(('Headcount Calc'!$B$6:$B$83=$A$6)*'Headcount Calc'!AD$6:AD$83*'Headcount Calc'!$I$6:$I$83) -> 30242.692 | ... M9: =SUMPRODUCT(('Headcount Calc'!$B$6:$B$83=$A$6)*'Headcount Calc'!AH$6:AH$83*'Headcount Calc'!$I$6:$I$83) -> 30242.692 | N9: =SUM(B9:M9) -> 337476.35
A10: Payroll taxes | B10: =(B8+B9)*Assumptions!$B$15 -> 17937.48 | C10: =(C8+C9)*Assumptions!$B$15 -> 18637.32 | D10: =(D8+D9)*Assumptions!$B$15 -> 18637.32 | E10: =(E8+E9)*Assumptions!$B$15 -> 19971.452 | F10: =(F8+F9)*Assumptions!$B$15 -> 19926.209 | G10: =(G8+G9)*Assumptions!$B$15 -> 20916.209 | H10: =(H8+H9)*Assumptions!$B$15 -> 22199.609 | I10: =(I8+I9)*Assumptions!$B$15 -> 22199.609 | ... M10: =(M8+M9)*Assumptions!$B$15 -> 22199.609 | N10: =SUM(B10:M10) -> 249223.64
A11: Benefits | B11: =B7*Assumptions!$B$16 -> 23000 | C11: =C7*Assumptions!$B$16 -> 24150 | D11: =D7*Assumptions!$B$16 -> 24150 | E11: =E7*Assumptions!$B$16 -> 25300 | F11: =F7*Assumptions!$B$16 -> 25300 | G11: =G7*Assumptions!$B$16 -> 26450 | H11: =H7*Assumptions!$B$16 -> 27600 | I11: =I7*Assumptions!$B$16 -> 27600 | ... M11: =M7*Assumptions!$B$16 -> 27600 | N11: =SUM(B11:M11) -> 313950
A12: Recruiting & onboarding | B12: =SUMPRODUCT(('Headcount Calc'!$B$6:$B$83=$A$6)*('Headcount Calc'!$C$6:$C$83="Open role")*('Headcount Calc'!$H$6:$H$83=1)*('Headcount Calc'!$F$6:$F$83>=B$4)*('Headcount Calc'!$F$6:$F$83<=EOMONTH(B$4,0))*'Headcount Calc'!$E$6:$E$83)*Assumptions!$B$19+SUMPRODUCT(('Headcount Calc'!$B$6:$B$83=$A$6)*('Headcount Calc'!$C$6:$C$83="Open role")*('Headcount Calc'!$H$6:$H$83=1)*('Headcount Calc'!$F$6:$F$83>=B$4)*('Headcount Calc'!$F$6:$F$83<=EOMONTH(B$4,0)))*Assumptions!$B$20 -> 0 | C12: =SUMPRODUCT(('Headcount Calc'!$B$6:$B$83=$A$6)*('Headcount Calc'!$C$6:$C$83="Open role")*('Headcount Calc'!$H$6:$H$83=1)*('Headcount Calc'!$F$6:$F$83>=C$4)*('Headcount Calc'!$F$6:$F$83<=EOMONTH(C$4,0))*'Headcount Calc'!$E$6:$E$83)*Assumptions!$B$19+SUMPRODUCT(('Headcount Calc'!$B$6:$B$83=$A$6)*('Headcount Calc'!$C$6:$C$83="Open role")*('Headcount Calc'!$H$6:$H$83=1)*('Headcount Calc'!$F$6:$F$83>=C$4)*('Headcount Calc'!$F$6:$F$83<=EOMONTH(C$4,0)))*Assumptions!$B$20 -> 19200 | D12: =SUMPRODUCT(('Headcount Calc'!$B$6:$B$83=$A$6)*('Headcount Calc'!$C$6:$C$83="Open role")*('Headcount Calc'!$H$6:$H$83=1)*('Headcount Calc'!$F$6:$F$83>=D$4)*('Headcount Calc'!$F$6:$F$83<=EOMONTH(D$4,0))*'Headcount Calc'!$E$6:$E$83)*Assumptions!$B$19+SUMPRODUCT(('Headcount Calc'!$B$6:$B$83=$A$6)*('Headcount Calc'!$C$6:$C$83="Open role")*('Headcount Calc'!$H$6:$H$83=1)*('Headcount Calc'!$F$6:$F$83>=D$4)*('Headcount Calc'!$F$6:$F$83<=EOMONTH(D$4,0)))*Assumptions!$B$20 -> 0 | E12: =SUMPRODUCT(('Headcount Calc'!$B$6:$B$83=$A$6)*('Headcount Calc'!$C$6:$C$83="Open role")*('Headcount Calc'!$H$6:$H$83=1)*('Headcount Calc'!$F$6:$F$83>=E$4)*('Headcount Calc'!$F$6:$F$83<=EOMONTH(E$4,0))*'Headcount Calc'!$E$6:$E$83)*Assumptions!$B$19+SUMPRODUCT(('Headcount Calc'!$B$6:$B$83=$A$6)*('Headcount Calc'!$C$6:$C$83="Open role")*('Headcount Calc'!$H$6:$H$83=1)*('Headcount Calc'!$F$6:$F$83>=E$4)*('Headcount Calc'!$F$6:$F$83<=EOMONTH(E$4,0)))*Assumptions!$B$20 -> 19350 | F12: =SUMPRODUCT(('Headcount Calc'!$B$6:$B$83=$A$6)*('Headcount Calc'!$C$6:$C$83="Open role")*('Headcount Calc'!$H$6:$H$83=1)*('Headcount Calc'!$F$6:$F$83>=F$4)*('Headcount Calc'!$F$6:$F$83<=EOMONTH(F$4,0))*'Headcount Calc'!$E$6:$E$83)*Assumptions!$B$19+SUMPRODUCT(('Headcount Calc'!$B$6:$B$83=$A$6)*('Headcount Calc'!$C$6:$C$83="Open role")*('Headcount Calc'!$H$6:$H$83=1)*('Headcount Calc'!$F$6:$F$83>=F$4)*('Headcount Calc'!$F$6:$F$83<=EOMONTH(F$4,0)))*Assumptions!$B$20 -> 25725 | G12: =SUMPRODUCT(('Headcount Calc'!$B$6:$B$83=$A$6)*('Headcount Calc'!$C$6:$C$83="Open role")*('Headcount Calc'!$H$6:$H$83=1)*('Headcount Calc'!$F$6:$F$83>=G$4)*('Headcount Calc'!$F$6:$F$83<=EOMONTH(G$4,0))*'Headcount Calc'!$E$6:$E$83)*Assumptions!$B$19+SUMPRODUCT(('Headcount Calc'!$B$6:$B$83=$A$6)*('Headcount Calc'!$C$6:$C$83="Open role")*('Headcount Calc'!$H$6:$H$83=1)*('Headcount Calc'!$F$6:$F$83>=G$4)*('Headcount Calc'!$F$6:$F$83<=EOMONTH(G$4,0)))*Assumptions!$B$20 -> 25500 | H12: =SUMPRODUCT(('Headcount Calc'!$B$6:$B$83=$A$6)*('Headcount Calc'!$C$6:$C$83="Open role")*('Headcount Calc'!$H$6:$H$83=1)*('Headcount Calc'!$F$6:$F$83>=H$4)*('Headcount Calc'!$F$6:$F$83<=EOMONTH(H$4,0))*'Headcount Calc'!$E$6:$E$83)*Assumptions!$B$19+SUMPRODUCT(('Headcount Calc'!$B$6:$B$83=$A$6)*('Headcount Calc'!$C$6:$C$83="Open role")*('Headcount Calc'!$H$6:$H$83=1)*('Headcount Calc'!$F$6:$F$83>=H$4)*('Headcount Calc'!$F$6:$F$83<=EOMONTH(H$4,0)))*Assumptions!$B$20 -> 30900 | I12: =SUMPRODUCT(('Headcount Calc'!$B$6:$B$83=$A$6)*('Headcount Calc'!$C$6:$C$83="Open role")*('Headcount Calc'!$H$6:$H$83=1)*('Headcount Calc'!$F$6:$F$83>=I$4)*('Headcount Calc'!$F$6:$F$83<=EOMONTH(I$4,0))*'Headcount Calc'!$E$6:$E$83)*Assumptions!$B$19+SUMPRODUCT(('Headcount Calc'!$B$6:$B$83=$A$6)*('Headcount Calc'!$C$6:$C$83="Open role")*('Headcount Calc'!$H$6:$H$83=1)*('Headcount Calc'!$F$6:$F$83>=I$4)*('Headcount Calc'!$F$6:$F$83<=EOMONTH(I$4,0)))*Assumptions!$B$20 -> 0 | ... M12: =SUMPRODUCT(('Headcount Calc'!$B$6:$B$83=$A$6)*('Headcount Calc'!$C$6:$C$83="Open role")*('Headcount Calc'!$H$6:$H$83=1)*('Headcount Calc'!$F$6:$F$83>=M$4)*('Headcount Calc'!$F$6:$F$83<=EOMONTH(M$4,0))*'Headcount Calc'!$E$6:$E$83)*Assumptions!$B$19+SUMPRODUCT(('Headcount Calc'!$B$6:$B$83=$A$6)*('Headcount Calc'!$C$6:$C$83="Open role")*('Headcount Calc'!$H$6:$H$83=1)*('Headcount Calc'!$F$6:$F$83>=M$4)*('Headcount Calc'!$F$6:$F$83<=EOMONTH(M$4,0)))*Assumptions!$B$20 -> 0 | N12: =SUM(B12:M12) -> 120675
A13: Software & tools | B13: =B7*Assumptions!$B$21 -> 5000 | C13: =C7*Assumptions!$B$21 -> 5250 | D13: =D7*Assumptions!$B$21 -> 5250 | E13: =E7*Assumptions!$B$21 -> 5500 | F13: =F7*Assumptions!$B$21 -> 5500 | G13: =G7*Assumptions!$B$21 -> 5750 | H13: =H7*Assumptions!$B$21 -> 6000 | I13: =I7*Assumptions!$B$21 -> 6000 | ... M13: =M7*Assumptions!$B$21 -> 6000 | N13: =SUM(B13:M13) -> 68250
A14: Travel & entertainment | B14: =B7*VLOOKUP($A$6,Assumptions!$A$35:$C$40,2,FALSE()) -> 3000 | C14: =C7*VLOOKUP($A$6,Assumptions!$A$35:$C$40,2,FALSE()) -> 3150 | D14: =D7*VLOOKUP($A$6,Assumptions!$A$35:$C$40,2,FALSE()) -> 3150 | E14: =E7*VLOOKUP($A$6,Assumptions!$A$35:$C$40,2,FALSE()) -> 3300 | F14: =F7*VLOOKUP($A$6,Assumptions!$A$35:$C$40,2,FALSE()) -> 3300 | G14: =G7*VLOOKUP($A$6,Assumptions!$A$35:$C$40,2,FALSE()) -> 3450 | H14: =H7*VLOOKUP($A$6,Assumptions!$A$35:$C$40,2,FALSE()) -> 3600 | I14: =I7*VLOOKUP($A$6,Assumptions!$A$35:$C$40,2,FALSE()) -> 3600 | ... M14: =M7*VLOOKUP($A$6,Assumptions!$A$35:$C$40,2,FALSE()) -> 3600 | N14: =SUM(B14:M14) -> 40950
A15: Facilities | B15: =B7*Assumptions!$B$22 -> 12000 | C15: =C7*Assumptions!$B$22 -> 12600 | D15: =D7*Assumptions!$B$22 -> 12600 | E15: =E7*Assumptions!$B$22 -> 13200 | F15: =F7*Assumptions!$B$22 -> 13200 | G15: =G7*Assumptions!$B$22 -> 13800 | H15: =H7*Assumptions!$B$22 -> 14400 | I15: =I7*Assumptions!$B$22 -> 14400 | ... M15: =M7*Assumptions!$B$22 -> 14400 | N15: =SUM(B15:M15) -> 163800
A16: Programs & vendors | B16: =VLOOKUP($A$6,Assumptions!$A$35:$C$40,3,FALSE())/12*(1+Assumptions!$F$11) -> 50000 | C16: =VLOOKUP($A$6,Assumptions!$A$35:$C$40,3,FALSE())/12*(1+Assumptions!$F$11) -> 50000 | D16: =VLOOKUP($A$6,Assumptions!$A$35:$C$40,3,FALSE())/12*(1+Assumptions!$F$11) -> 50000 | E16: =VLOOKUP($A$6,Assumptions!$A$35:$C$40,3,FALSE())/12*(1+Assumptions!$F$11) -> 50000 | F16: =VLOOKUP($A$6,Assumptions!$A$35:$C$40,3,FALSE())/12*(1+Assumptions!$F$11) -> 50000 | G16: =VLOOKUP($A$6,Assumptions!$A$35:$C$40,3,FALSE())/12*(1+Assumptions!$F$11) -> 50000 | H16: =VLOOKUP($A$6,Assumptions!$A$35:$C$40,3,FALSE())/12*(1+Assumptions!$F$11) -> 50000 | I16: =VLOOKUP($A$6,Assumptions!$A$35:$C$40,3,FALSE())/12*(1+Assumptions!$F$11) -> 50000 | ... M16: =VLOOKUP($A$6,Assumptions!$A$35:$C$40,3,FALSE())/12*(1+Assumptions!$F$11) -> 50000 | N16: =SUM(B16:M16) -> 600000
A17: Total operating expense | B17: =SUM(B8:B16) -> 360069.15 | C17: =SUM(C8:C16) -> 391838.99 | D17: =SUM(D8:D16) -> 372638.99 | E17: =SUM(E8:E16) -> 414002.73 | F17: =SUM(F8:F16) -> 419704.11 | G17: =SUM(G8:G16) -> 436369.11 | H17: =SUM(H8:H16) -> 463027.51 | I17: =SUM(I8:I16) -> 432127.51 | ... M17: =SUM(M8:M16) -> 432127.51 | N17: =SUM(B17:M17) -> 5018288.1
A19: Product
A20: FTE (average for the month) | B20: =SUMIF('Headcount Calc'!$B$6:$B$83,$A$19,'Headcount Calc'!K$6:K$83) -> 5 | C20: =SUMIF('Headcount Calc'!$B$6:$B$83,$A$19,'Headcount Calc'!L$6:L$83) -> 5 | D20: =SUMIF('Headcount Calc'!$B$6:$B$83,$A$19,'Headcount Calc'!M$6:M$83) -> 6 | E20: =SUMIF('Headcount Calc'!$B$6:$B$83,$A$19,'Headcount Calc'!N$6:N$83) -> 6 | F20: =SUMIF('Headcount Calc'!$B$6:$B$83,$A$19,'Headcount Calc'!O$6:O$83) -> 6 | G20: =SUMIF('Headcount Calc'!$B$6:$B$83,$A$19,'Headcount Calc'!P$6:P$83) -> 6 | H20: =SUMIF('Headcount Calc'!$B$6:$B$83,$A$19,'Headcount Calc'!Q$6:Q$83) -> 6 | I20: =SUMIF('Headcount Calc'!$B$6:$B$83,$A$19,'Headcount Calc'!R$6:R$83) -> 6 | ... M20: =SUMIF('Headcount Calc'!$B$6:$B$83,$A$19,'Headcount Calc'!V$6:V$83) -> 6 | N20: =AVERAGE(B20:M20) -> 5.8333333
A21: Salaries | B21: =SUMIF('Headcount Calc'!$B$6:$B$83,$A$19,'Headcount Calc'!W$6:W$83) -> 61041.667 | C21: =SUMIF('Headcount Calc'!$B$6:$B$83,$A$19,'Headcount Calc'!X$6:X$83) -> 61041.667 | D21: =SUMIF('Headcount Calc'!$B$6:$B$83,$A$19,'Headcount Calc'!Y$6:Y$83) -> 72666.667 | E21: =SUMIF('Headcount Calc'!$B$6:$B$83,$A$19,'Headcount Calc'!Z$6:Z$83) -> 74803.125 | F21: =SUMIF('Headcount Calc'!$B$6:$B$83,$A$19,'Headcount Calc'!AA$6:AA$83) -> 74803.125 | G21: =SUMIF('Headcount Calc'!$B$6:$B$83,$A$19,'Headcount Calc'!AB$6:AB$83) -> 74803.125 | H21: =SUMIF('Headcount Calc'!$B$6:$B$83,$A$19,'Headcount Calc'!AC$6:AC$83) -> 74803.125 | I21: =SUMIF('Headcount Calc'!$B$6:$B$83,$A$19,'Headcount Calc'!AD$6:AD$83) -> 74803.125 | ... M21: =SUMIF('Headcount Calc'!$B$6:$B$83,$A$19,'Headcount Calc'!AH$6:AH$83) -> 74803.125 | N21: =SUM(B21:M21) -> 867978.12
A22: Bonus & variable compensation | B22: =SUMPRODUCT(('Headcount Calc'!$B$6:$B$83=$A$19)*'Headcount Calc'!W$6:W$83*'Headcount Calc'!$I$6:$I$83) -> 7777.5 | C22: =SUMPRODUCT(('Headcount Calc'!$B$6:$B$83=$A$19)*'Headcount Calc'!X$6:X$83*'Headcount Calc'!$I$6:$I$83) -> 7777.5 | D22: =SUMPRODUCT(('Headcount Calc'!$B$6:$B$83=$A$19)*'Headcount Calc'!Y$6:Y$83*'Headcount Calc'!$I$6:$I$83) -> 8940 | E22: =SUMPRODUCT(('Headcount Calc'!$B$6:$B$83=$A$19)*'Headcount Calc'!Z$6:Z$83*'Headcount Calc'!$I$6:$I$83) -> 9212.2125 | F22: =SUMPRODUCT(('Headcount Calc'!$B$6:$B$83=$A$19)*'Headcount Calc'!AA$6:AA$83*'Headcount Calc'!$I$6:$I$83) -> 9212.2125 | G22: =SUMPRODUCT(('Headcount Calc'!$B$6:$B$83=$A$19)*'Headcount Calc'!AB$6:AB$83*'Headcount Calc'!$I$6:$I$83) -> 9212.2125 | H22: =SUMPRODUCT(('Headcount Calc'!$B$6:$B$83=$A$19)*'Headcount Calc'!AC$6:AC$83*'Headcount Calc'!$I$6:$I$83) -> 9212.2125 | I22: =SUMPRODUCT(('Headcount Calc'!$B$6:$B$83=$A$19)*'Headcount Calc'!AD$6:AD$83*'Headcount Calc'!$I$6:$I$83) -> 9212.2125 | ... M22: =SUMPRODUCT(('Headcount Calc'!$B$6:$B$83=$A$19)*'Headcount Calc'!AH$6:AH$83*'Headcount Calc'!$I$6:$I$83) -> 9212.2125 | N22: =SUM(B22:M22) -> 107404.91
A23: Payroll taxes | B23: =(B21+B22)*Assumptions!$B$15 -> 4954.98 | C23: =(C21+C22)*Assumptions!$B$15 -> 4954.98 | D23: =(D21+D22)*Assumptions!$B$15 -> 5875.68 | E23: =(E21+E22)*Assumptions!$B$15 -> 6049.1043 | F23: =(F21+F22)*Assumptions!$B$15 -> 6049.1043 | G23: =(G21+G22)*Assumptions!$B$15 -> 6049.1043 | H23: =(H21+H22)*Assumptions!$B$15 -> 6049.1043 | I23: =(I21+I22)*Assumptions!$B$15 -> 6049.1043 | ... M23: =(M21+M22)*Assumptions!$B$15 -> 6049.1043 | N23: =SUM(B23:M23) -> 70227.579
A24: Benefits | B24: =B20*Assumptions!$B$16 -> 5750 | C24: =C20*Assumptions!$B$16 -> 5750 | D24: =D20*Assumptions!$B$16 -> 6900 | E24: =E20*Assumptions!$B$16 -> 6900 | F24: =F20*Assumptions!$B$16 -> 6900 | G24: =G20*Assumptions!$B$16 -> 6900 | H24: =H20*Assumptions!$B$16 -> 6900 | I24: =I20*Assumptions!$B$16 -> 6900 | ... M24: =M20*Assumptions!$B$16 -> 6900 | N24: =SUM(B24:M24) -> 80500
A25: Recruiting & onboarding | B25: =SUMPRODUCT(('Headcount Calc'!$B$6:$B$83=$A$19)*('Headcount Calc'!$C$6:$C$83="Open role")*('Headcount Calc'!$H$6:$H$83=1)*('Headcount Calc'!$F$6:$F$83>=B$4)*('Headcount Calc'!$F$6:$F$83<=EOMONTH(B$4,0))*'Headcount Calc'!$E$6:$E$83)*Assumptions!$B$19+SUMPRODUCT(('Headcount Calc'!$B$6:$B$83=$A$19)*('Headcount Calc'!$C$6:$C$83="Open role")*('Headcount Calc'!$H$6:$H$83=1)*('Headcount Calc'!$F$6:$F$83>=B$4)*('Headcount Calc'!$F$6:$F$83<=EOMONTH(B$4,0)))*Assumptions!$B$20 -> 0 | C25: =SUMPRODUCT(('Headcount Calc'!$B$6:$B$83=$A$19)*('Headcount Calc'!$C$6:$C$83="Open role")*('Headcount Calc'!$H$6:$H$83=1)*('Headcount Calc'!$F$6:$F$83>=C$4)*('Headcount Calc'!$F$6:$F$83<=EOMONTH(C$4,0))*'Headcount Calc'!$E$6:$E$83)*Assumptions!$B$19+SUMPRODUCT(('Headcount Calc'!$B$6:$B$83=$A$19)*('Headcount Calc'!$C$6:$C$83="Open role")*('Headcount Calc'!$H$6:$H$83=1)*('Headcount Calc'!$F$6:$F$83>=C$4)*('Headcount Calc'!$F$6:$F$83<=EOMONTH(C$4,0)))*Assumptions!$B$20 -> 0 | D25: =SUMPRODUCT(('Headcount Calc'!$B$6:$B$83=$A$19)*('Headcount Calc'!$C$6:$C$83="Open role")*('Headcount Calc'!$H$6:$H$83=1)*('Headcount Calc'!$F$6:$F$83>=D$4)*('Headcount Calc'!$F$6:$F$83<=EOMONTH(D$4,0))*'Headcount Calc'!$E$6:$E$83)*Assumptions!$B$19+SUMPRODUCT(('Headcount Calc'!$B$6:$B$83=$A$19)*('Headcount Calc'!$C$6:$C$83="Open role")*('Headcount Calc'!$H$6:$H$83=1)*('Headcount Calc'!$F$6:$F$83>=D$4)*('Headcount Calc'!$F$6:$F$83<=EOMONTH(D$4,0)))*Assumptions!$B$20 -> 23925 | E25: =SUMPRODUCT(('Headcount Calc'!$B$6:$B$83=$A$19)*('Headcount Calc'!$C$6:$C$83="Open role")*('Headcount Calc'!$H$6:$H$83=1)*('Headcount Calc'!$F$6:$F$83>=E$4)*('Headcount Calc'!$F$6:$F$83<=EOMONTH(E$4,0))*'Headcount Calc'!$E$6:$E$83)*Assumptions!$B$19+SUMPRODUCT(('Headcount Calc'!$B$6:$B$83=$A$19)*('Headcount Calc'!$C$6:$C$83="Open role")*('Headcount Calc'!$H$6:$H$83=1)*('Headcount Calc'!$F$6:$F$83>=E$4)*('Headcount Calc'!$F$6:$F$83<=EOMONTH(E$4,0)))*Assumptions!$B$20 -> 0 | F25: =SUMPRODUCT(('Headcount Calc'!$B$6:$B$83=$A$19)*('Headcount Calc'!$C$6:$C$83="Open role")*('Headcount Calc'!$H$6:$H$83=1)*('Headcount Calc'!$F$6:$F$83>=F$4)*('Headcount Calc'!$F$6:$F$83<=EOMONTH(F$4,0))*'Headcount Calc'!$E$6:$E$83)*Assumptions!$B$19+SUMPRODUCT(('Headcount Calc'!$B$6:$B$83=$A$19)*('Headcount Calc'!$C$6:$C$83="Open role")*('Headcount Calc'!$H$6:$H$83=1)*('Headcount Calc'!$F$6:$F$83>=F$4)*('Headcount Calc'!$F$6:$F$83<=EOMONTH(F$4,0)))*Assumptions!$B$20 -> 0 | G25: =SUMPRODUCT(('Headcount Calc'!$B$6:$B$83=$A$19)*('Headcount Calc'!$C$6:$C$83="Open role")*('Headcount Calc'!$H$6:$H$83=1)*('Headcount Calc'!$F$6:$F$83>=G$4)*('Headcount Calc'!$F$6:$F$83<=EOMONTH(G$4,0))*'Headcount Calc'!$E$6:$E$83)*Assumptions!$B$19+SUMPRODUCT(('Headcount Calc'!$B$6:$B$83=$A$19)*('Headcount Calc'!$C$6:$C$83="Open role")*('Headcount Calc'!$H$6:$H$83=1)*('Headcount Calc'!$F$6:$F$83>=G$4)*('Headcount Calc'!$F$6:$F$83<=EOMONTH(G$4,0)))*Assumptions!$B$20 -> 0 | H25: =SUMPRODUCT(('Headcount Calc'!$B$6:$B$83=$A$19)*('Headcount Calc'!$C$6:$C$83="Open role")*('Headcount Calc'!$H$6:$H$83=1)*('Headcount Calc'!$F$6:$F$83>=H$4)*('Headcount Calc'!$F$6:$F$83<=EOMONTH(H$4,0))*'Headcount Calc'!$E$6:$E$83)*Assumptions!$B$19+SUMPRODUCT(('Headcount Calc'!$B$6:$B$83=$A$19)*('Headcount Calc'!$C$6:$C$83="Open role")*('Headcount Calc'!$H$6:$H$83=1)*('Headcount Calc'!$F$6:$F$83>=H$4)*('Headcount Calc'!$F$6:$F$83<=EOMONTH(H$4,0)))*Assumptions!$B$20 -> 0 | I25: =SUMPRODUCT(('Headcount Calc'!$B$6:$B$83=$A$19)*('Headcount Calc'!$C$6:$C$83="Open role")*('Headcount Calc'!$H$6:$H$83=1)*('Headcount Calc'!$F$6:$F$83>=I$4)*('Headcount Calc'!$F$6:$F$83<=EOMONTH(I$4,0))*'Headcount Calc'!$E$6:$E$83)*Assumptions!$B$19+SUMPRODUCT(('Headcount Calc'!$B$6:$B$83=$A$19)*('Headcount Calc'!$C$6:$C$83="Open role")*('Headcount Calc'!$H$6:$H$83=1)*('Headcount Calc'!$F$6:$F$83>=I$4)*('Headcount Calc'!$F$6:$F$83<=EOMONTH(I$4,0)))*Assumptions!$B$20 -> 0 | ... M25: =SUMPRODUCT(('Headcount Calc'!$B$6:$B$83=$A$19)*('Headcount Calc'!$C$6:$C$83="Open role")*('Headcount Calc'!$H$6:$H$83=1)*('Headcount Calc'!$F$6:$F$83>=M$4)*('Headcount Calc'!$F$6:$F$83<=EOMONTH(M$4,0))*'Headcount Calc'!$E$6:$E$83)*Assumptions!$B$19+SUMPRODUCT(('Headcount Calc'!$B$6:$B$83=$A$19)*('Headcount Calc'!$C$6:$C$83="Open role")*('Headcount Calc'!$H$6:$H$83=1)*('Headcount Calc'!$F$6:$F$83>=M$4)*('Headcount Calc'!$F$6:$F$83<=EOMONTH(M$4,0)))*Assumptions!$B$20 -> 0 | N25: =SUM(B25:M25) -> 23925
A26: Software & tools | B26: =B20*Assumptions!$B$21 -> 1250 | C26: =C20*Assumptions!$B$21 -> 1250 | D26: =D20*Assumptions!$B$21 -> 1500 | E26: =E20*Assumptions!$B$21 -> 1500 | F26: =F20*Assumptions!$B$21 -> 1500 | G26: =G20*Assumptions!$B$21 -> 1500 | H26: =H20*Assumptions!$B$21 -> 1500 | I26: =I20*Assumptions!$B$21 -> 1500 | ... M26: =M20*Assumptions!$B$21 -> 1500 | N26: =SUM(B26:M26) -> 17500
A27: Travel & entertainment | B27: =B20*VLOOKUP($A$19,Assumptions!$A$35:$C$40,2,FALSE()) -> 1000 | C27: =C20*VLOOKUP($A$19,Assumptions!$A$35:$C$40,2,FALSE()) -> 1000 | D27: =D20*VLOOKUP($A$19,Assumptions!$A$35:$C$40,2,FALSE()) -> 1200 | E27: =E20*VLOOKUP($A$19,Assumptions!$A$35:$C$40,2,FALSE()) -> 1200 | F27: =F20*VLOOKUP($A$19,Assumptions!$A$35:$C$40,2,FALSE()) -> 1200 | G27: =G20*VLOOKUP($A$19,Assumptions!$A$35:$C$40,2,FALSE()) -> 1200 | H27: =H20*VLOOKUP($A$19,Assumptions!$A$35:$C$40,2,FALSE()) -> 1200 | I27: =I20*VLOOKUP($A$19,Assumptions!$A$35:$C$40,2,FALSE()) -> 1200 | ... M27: =M20*VLOOKUP($A$19,Assumptions!$A$35:$C$40,2,FALSE()) -> 1200 | N27: =SUM(B27:M27) -> 14000
A28: Facilities | B28: =B20*Assumptions!$B$22 -> 3000 | C28: =C20*Assumptions!$B$22 -> 3000 | D28: =D20*Assumptions!$B$22 -> 3600 | E28: =E20*Assumptions!$B$22 -> 3600 | F28: =F20*Assumptions!$B$22 -> 3600 | G28: =G20*Assumptions!$B$22 -> 3600 | H28: =H20*Assumptions!$B$22 -> 3600 | I28: =I20*Assumptions!$B$22 -> 3600 | ... M28: =M20*Assumptions!$B$22 -> 3600 | N28: =SUM(B28:M28) -> 42000
A29: Programs & vendors | B29: =VLOOKUP($A$19,Assumptions!$A$35:$C$40,3,FALSE())/12*(1+Assumptions!$F$11) -> 8333.3333 | C29: =VLOOKUP($A$19,Assumptions!$A$35:$C$40,3,FALSE())/12*(1+Assumptions!$F$11) -> 8333.3333 | D29: =VLOOKUP($A$19,Assumptions!$A$35:$C$40,3,FALSE())/12*(1+Assumptions!$F$11) -> 8333.3333 | E29: =VLOOKUP($A$19,Assumptions!$A$35:$C$40,3,FALSE())/12*(1+Assumptions!$F$11) -> 8333.3333 | F29: =VLOOKUP($A$19,Assumptions!$A$35:$C$40,3,FALSE())/12*(1+Assumptions!$F$11) -> 8333.3333 | G29: =VLOOKUP($A$19,Assumptions!$A$35:$C$40,3,FALSE())/12*(1+Assumptions!$F$11) -> 8333.3333 | H29: =VLOOKUP($A$19,Assumptions!$A$35:$C$40,3,FALSE())/12*(1+Assumptions!$F$11) -> 8333.3333 | I29: =VLOOKUP($A$19,Assumptions!$A$35:$C$40,3,FALSE())/12*(1+Assumptions!$F$11) -> 8333.3333 | ... M29: =VLOOKUP($A$19,Assumptions!$A$35:$C$40,3,FALSE())/12*(1+Assumptions!$F$11) -> 8333.3333 | N29: =SUM(B29:M29) -> 100000
A30: Total operating expense | B30: =SUM(B21:B29) -> 93107.48 | C30: =SUM(C21:C29) -> 93107.48 | D30: =SUM(D21:D29) -> 132940.68 | E30: =SUM(E21:E29) -> 111597.78 | F30: =SUM(F21:F29) -> 111597.78 | G30: =SUM(G21:G29) -> 111597.78 | H30: =SUM(H21:H29) -> 111597.78 | I30: =SUM(I21:I29) -> 111597.78 | ... M30: =SUM(M21:M29) -> 111597.78 | N30: =SUM(B30:M30) -> 1323535.6
A32: Sales
A33: FTE (average for the month) | B33: =SUMIF('Headcount Calc'!$B$6:$B$83,$A$32,'Headcount Calc'!K$6:K$83) -> 12 | C33: =SUMIF('Headcount Calc'!$B$6:$B$83,$A$32,'Headcount Calc'!L$6:L$83) -> 12 | D33: =SUMIF('Headcount Calc'!$B$6:$B$83,$A$32,'Headcount Calc'!M$6:M$83) -> 13 | E33: =SUMIF('Headcount Calc'!$B$6:$B$83,$A$32,'Headcount Calc'!N$6:N$83) -> 13 | F33: =SUMIF('Headcount Calc'!$B$6:$B$83,$A$32,'Headcount Calc'!O$6:O$83) -> 13 | G33: =SUMIF('Headcount Calc'!$B$6:$B$83,$A$32,'Headcount Calc'!P$6:P$83) -> 14 | H33: =SUMIF('Headcount Calc'!$B$6:$B$83,$A$32,'Headcount Calc'!Q$6:Q$83) -> 14 | I33: =SUMIF('Headcount Calc'!$B$6:$B$83,$A$32,'Headcount Calc'!R$6:R$83) -> 14 | ... M33: =SUMIF('Headcount Calc'!$B$6:$B$83,$A$32,'Headcount Calc'!V$6:V$83) -> 14 | N33: =AVERAGE(B33:M33) -> 13.416667
A34: Salaries | B34: =SUMIF('Headcount Calc'!$B$6:$B$83,$A$32,'Headcount Calc'!W$6:W$83) -> 93083.333 | C34: =SUMIF('Headcount Calc'!$B$6:$B$83,$A$32,'Headcount Calc'!X$6:X$83) -> 93083.333 | D34: =SUMIF('Headcount Calc'!$B$6:$B$83,$A$32,'Headcount Calc'!Y$6:Y$83) -> 99750 | E34: =SUMIF('Headcount Calc'!$B$6:$B$83,$A$32,'Headcount Calc'!Z$6:Z$83) -> 103007.92 | F34: =SUMIF('Headcount Calc'!$B$6:$B$83,$A$32,'Headcount Calc'!AA$6:AA$83) -> 103007.92 | G34: =SUMIF('Headcount Calc'!$B$6:$B$83,$A$32,'Headcount Calc'!AB$6:AB$83) -> 109757.92 | H34: =SUMIF('Headcount Calc'!$B$6:$B$83,$A$32,'Headcount Calc'!AC$6:AC$83) -> 109990.21 | I34: =SUMIF('Headcount Calc'!$B$6:$B$83,$A$32,'Headcount Calc'!AD$6:AD$83) -> 109990.21 | ... M34: =SUMIF('Headcount Calc'!$B$6:$B$83,$A$32,'Headcount Calc'!AH$6:AH$83) -> 109990.21 | N34: =SUM(B34:M34) -> 1261631.7
A35: Bonus & variable compensation | B35: =SUMPRODUCT(('Headcount Calc'!$B$6:$B$83=$A$32)*'Headcount Calc'!W$6:W$83*'Headcount Calc'!$I$6:$I$83) -> 27925 | C35: =SUMPRODUCT(('Headcount Calc'!$B$6:$B$83=$A$32)*'Headcount Calc'!X$6:X$83*'Headcount Calc'!$I$6:$I$83) -> 27925 | D35: =SUMPRODUCT(('Headcount Calc'!$B$6:$B$83=$A$32)*'Headcount Calc'!Y$6:Y$83*'Headcount Calc'!$I$6:$I$83) -> 29925 | E35: =SUMPRODUCT(('Headcount Calc'!$B$6:$B$83=$A$32)*'Headcount Calc'!Z$6:Z$83*'Headcount Calc'!$I$6:$I$83) -> 30902.375 | F35: =SUMPRODUCT(('Headcount Calc'!$B$6:$B$83=$A$32)*'Headcount Calc'!AA$6:AA$83*'Headcount Calc'!$I$6:$I$83) -> 30902.375 | G35: =SUMPRODUCT(('Headcount Calc'!$B$6:$B$83=$A$32)*'Headcount Calc'!AB$6:AB$83*'Headcount Calc'!$I$6:$I$83) -> 32927.375 | H35: =SUMPRODUCT(('Headcount Calc'!$B$6:$B$83=$A$32)*'Headcount Calc'!AC$6:AC$83*'Headcount Calc'!$I$6:$I$83) -> 32997.062 | I35: =SUMPRODUCT(('Headcount Calc'!$B$6:$B$83=$A$32)*'Headcount Calc'!AD$6:AD$83*'Headcount Calc'!$I$6:$I$83) -> 32997.062 | ... M35: =SUMPRODUCT(('Headcount Calc'!$B$6:$B$83=$A$32)*'Headcount Calc'!AH$6:AH$83*'Headcount Calc'!$I$6:$I$83) -> 32997.062 | N35: =SUM(B35:M35) -> 378489.5
A36: Payroll taxes | B36: =(B34+B35)*Assumptions!$B$15 -> 8712.6 | C36: =(C34+C35)*Assumptions!$B$15 -> 8712.6 | D36: =(D34+D35)*Assumptions!$B$15 -> 9336.6 | E36: =(E34+E35)*Assumptions!$B$15 -> 9641.541 | F36: =(F34+F35)*Assumptions!$B$15 -> 9641.541 | G36: =(G34+G35)*Assumptions!$B$15 -> 10273.341 | H36: =(H34+H35)*Assumptions!$B$15 -> 10295.084 | I36: =(I34+I35)*Assumptions!$B$15 -> 10295.084 | ... M36: =(M34+M35)*Assumptions!$B$15 -> 10295.084 | N36: =SUM(B36:M36) -> 118088.72
A37: Benefits | B37: =B33*Assumptions!$B$16 -> 13800 | C37: =C33*Assumptions!$B$16 -> 13800 | D37: =D33*Assumptions!$B$16 -> 14950 | E37: =E33*Assumptions!$B$16 -> 14950 | F37: =F33*Assumptions!$B$16 -> 14950 | G37: =G33*Assumptions!$B$16 -> 16100 | H37: =H33*Assumptions!$B$16 -> 16100 | I37: =I33*Assumptions!$B$16 -> 16100 | ... M37: =M33*Assumptions!$B$16 -> 16100 | N37: =SUM(B37:M37) -> 185150
A38: Recruiting & onboarding | B38: =SUMPRODUCT(('Headcount Calc'!$B$6:$B$83=$A$32)*('Headcount Calc'!$C$6:$C$83="Open role")*('Headcount Calc'!$H$6:$H$83=1)*('Headcount Calc'!$F$6:$F$83>=B$4)*('Headcount Calc'!$F$6:$F$83<=EOMONTH(B$4,0))*'Headcount Calc'!$E$6:$E$83)*Assumptions!$B$19+SUMPRODUCT(('Headcount Calc'!$B$6:$B$83=$A$32)*('Headcount Calc'!$C$6:$C$83="Open role")*('Headcount Calc'!$H$6:$H$83=1)*('Headcount Calc'!$F$6:$F$83>=B$4)*('Headcount Calc'!$F$6:$F$83<=EOMONTH(B$4,0)))*Assumptions!$B$20 -> 0 | C38: =SUMPRODUCT(('Headcount Calc'!$B$6:$B$83=$A$32)*('Headcount Calc'!$C$6:$C$83="Open role")*('Headcount Calc'!$H$6:$H$83=1)*('Headcount Calc'!$F$6:$F$83>=C$4)*('Headcount Calc'!$F$6:$F$83<=EOMONTH(C$4,0))*'Headcount Calc'!$E$6:$E$83)*Assumptions!$B$19+SUMPRODUCT(('Headcount Calc'!$B$6:$B$83=$A$32)*('Headcount Calc'!$C$6:$C$83="Open role")*('Headcount Calc'!$H$6:$H$83=1)*('Headcount Calc'!$F$6:$F$83>=C$4)*('Headcount Calc'!$F$6:$F$83<=EOMONTH(C$4,0)))*Assumptions!$B$20 -> 0 | D38: =SUMPRODUCT(('Headcount Calc'!$B$6:$B$83=$A$32)*('Headcount Calc'!$C$6:$C$83="Open role")*('Headcount Calc'!$H$6:$H$83=1)*('Headcount Calc'!$F$6:$F$83>=D$4)*('Headcount Calc'!$F$6:$F$83<=EOMONTH(D$4,0))*'Headcount Calc'!$E$6:$E$83)*Assumptions!$B$19+SUMPRODUCT(('Headcount Calc'!$B$6:$B$83=$A$32)*('Headcount Calc'!$C$6:$C$83="Open role")*('Headcount Calc'!$H$6:$H$83=1)*('Headcount Calc'!$F$6:$F$83>=D$4)*('Headcount Calc'!$F$6:$F$83<=EOMONTH(D$4,0)))*Assumptions!$B$20 -> 15000 | E38: =SUMPRODUCT(('Headcount Calc'!$B$6:$B$83=$A$32)*('Headcount Calc'!$C$6:$C$83="Open role")*('Headcount Calc'!$H$6:$H$83=1)*('Headcount Calc'!$F$6:$F$83>=E$4)*('Headcount Calc'!$F$6:$F$83<=EOMONTH(E$4,0))*'Headcount Calc'!$E$6:$E$83)*Assumptions!$B$19+SUMPRODUCT(('Headcount Calc'!$B$6:$B$83=$A$32)*('Headcount Calc'!$C$6:$C$83="Open role")*('Headcount Calc'!$H$6:$H$83=1)*('Headcount Calc'!$F$6:$F$83>=E$4)*('Headcount Calc'!$F$6:$F$83<=EOMONTH(E$4,0)))*Assumptions!$B$20 -> 0 | F38: =SUMPRODUCT(('Headcount Calc'!$B$6:$B$83=$A$32)*('Headcount Calc'!$C$6:$C$83="Open role")*('Headcount Calc'!$H$6:$H$83=1)*('Headcount Calc'!$F$6:$F$83>=F$4)*('Headcount Calc'!$F$6:$F$83<=EOMONTH(F$4,0))*'Headcount Calc'!$E$6:$E$83)*Assumptions!$B$19+SUMPRODUCT(('Headcount Calc'!$B$6:$B$83=$A$32)*('Headcount Calc'!$C$6:$C$83="Open role")*('Headcount Calc'!$H$6:$H$83=1)*('Headcount Calc'!$F$6:$F$83>=F$4)*('Headcount Calc'!$F$6:$F$83<=EOMONTH(F$4,0)))*Assumptions!$B$20 -> 0 | G38: =SUMPRODUCT(('Headcount Calc'!$B$6:$B$83=$A$32)*('Headcount Calc'!$C$6:$C$83="Open role")*('Headcount Calc'!$H$6:$H$83=1)*('Headcount Calc'!$F$6:$F$83>=G$4)*('Headcount Calc'!$F$6:$F$83<=EOMONTH(G$4,0))*'Headcount Calc'!$E$6:$E$83)*Assumptions!$B$19+SUMPRODUCT(('Headcount Calc'!$B$6:$B$83=$A$32)*('Headcount Calc'!$C$6:$C$83="Open role")*('Headcount Calc'!$H$6:$H$83=1)*('Headcount Calc'!$F$6:$F$83>=G$4)*('Headcount Calc'!$F$6:$F$83<=EOMONTH(G$4,0)))*Assumptions!$B$20 -> 15150 | H38: =SUMPRODUCT(('Headcount Calc'!$B$6:$B$83=$A$32)*('Headcount Calc'!$C$6:$C$83="Open role")*('Headcount Calc'!$H$6:$H$83=1)*('Headcount Calc'!$F$6:$F$83>=H$4)*('Headcount Calc'!$F$6:$F$83<=EOMONTH(H$4,0))*'Headcount Calc'!$E$6:$E$83)*Assumptions!$B$19+SUMPRODUCT(('Headcount Calc'!$B$6:$B$83=$A$32)*('Headcount Calc'!$C$6:$C$83="Open role")*('Headcount Calc'!$H$6:$H$83=1)*('Headcount Calc'!$F$6:$F$83>=H$4)*('Headcount Calc'!$F$6:$F$83<=EOMONTH(H$4,0)))*Assumptions!$B$20 -> 15450 | I38: =SUMPRODUCT(('Headcount Calc'!$B$6:$B$83=$A$32)*('Headcount Calc'!$C$6:$C$83="Open role")*('Headcount Calc'!$H$6:$H$83=1)*('Headcount Calc'!$F$6:$F$83>=I$4)*('Headcount Calc'!$F$6:$F$83<=EOMONTH(I$4,0))*'Headcount Calc'!$E$6:$E$83)*Assumptions!$B$19+SUMPRODUCT(('Headcount Calc'!$B$6:$B$83=$A$32)*('Headcount Calc'!$C$6:$C$83="Open role")*('Headcount Calc'!$H$6:$H$83=1)*('Headcount Calc'!$F$6:$F$83>=I$4)*('Headcount Calc'!$F$6:$F$83<=EOMONTH(I$4,0)))*Assumptions!$B$20 -> 0 | ... M38: =SUMPRODUCT(('Headcount Calc'!$B$6:$B$83=$A$32)*('Headcount Calc'!$C$6:$C$83="Open role")*('Headcount Calc'!$H$6:$H$83=1)*('Headcount Calc'!$F$6:$F$83>=M$4)*('Headcount Calc'!$F$6:$F$83<=EOMONTH(M$4,0))*'Headcount Calc'!$E$6:$E$83)*Assumptions!$B$19+SUMPRODUCT(('Headcount Calc'!$B$6:$B$83=$A$32)*('Headcount Calc'!$C$6:$C$83="Open role")*('Headcount Calc'!$H$6:$H$83=1)*('Headcount Calc'!$F$6:$F$83>=M$4)*('Headcount Calc'!$F$6:$F$83<=EOMONTH(M$4,0)))*Assumptions!$B$20 -> 0 | N38: =SUM(B38:M38) -> 45600
A39: Software & tools | B39: =B33*Assumptions!$B$21 -> 3000 | C39: =C33*Assumptions!$B$21 -> 3000 | D39: =D33*Assumptions!$B$21 -> 3250 | E39: =E33*Assumptions!$B$21 -> 3250 | F39: =F33*Assumptions!$B$21 -> 3250 | G39: =G33*Assumptions!$B$21 -> 3500 | H39: =H33*Assumptions!$B$21 -> 3500 | I39: =I33*Assumptions!$B$21 -> 3500 | ... M39: =M33*Assumptions!$B$21 -> 3500 | N39: =SUM(B39:M39) -> 40250
A40: Travel & entertainment | B40: =B33*VLOOKUP($A$32,Assumptions!$A$35:$C$40,2,FALSE()) -> 14400 | C40: =C33*VLOOKUP($A$32,Assumptions!$A$35:$C$40,2,FALSE()) -> 14400 | D40: =D33*VLOOKUP($A$32,Assumptions!$A$35:$C$40,2,FALSE()) -> 15600 | E40: =E33*VLOOKUP($A$32,Assumptions!$A$35:$C$40,2,FALSE()) -> 15600 | F40: =F33*VLOOKUP($A$32,Assumptions!$A$35:$C$40,2,FALSE()) -> 15600 | G40: =G33*VLOOKUP($A$32,Assumptions!$A$35:$C$40,2,FALSE()) -> 16800 | H40: =H33*VLOOKUP($A$32,Assumptions!$A$35:$C$40,2,FALSE()) -> 16800 | I40: =I33*VLOOKUP($A$32,Assumptions!$A$35:$C$40,2,FALSE()) -> 16800 | ... M40: =M33*VLOOKUP($A$32,Assumptions!$A$35:$C$40,2,FALSE()) -> 16800 | N40: =SUM(B40:M40) -> 193200
A41: Facilities | B41: =B33*Assumptions!$B$22 -> 7200 | C41: =C33*Assumptions!$B$22 -> 7200 | D41: =D33*Assumptions!$B$22 -> 7800 | E41: =E33*Assumptions!$B$22 -> 7800 | F41: =F33*Assumptions!$B$22 -> 7800 | G41: =G33*Assumptions!$B$22 -> 8400 | H41: =H33*Assumptions!$B$22 -> 8400 | I41: =I33*Assumptions!$B$22 -> 8400 | ... M41: =M33*Assumptions!$B$22 -> 8400 | N41: =SUM(B41:M41) -> 96600
A42: Programs & vendors | B42: =VLOOKUP($A$32,Assumptions!$A$35:$C$40,3,FALSE())/12*(1+Assumptions!$F$11) -> 25000 | C42: =VLOOKUP($A$32,Assumptions!$A$35:$C$40,3,FALSE())/12*(1+Assumptions!$F$11) -> 25000 | D42: =VLOOKUP($A$32,Assumptions!$A$35:$C$40,3,FALSE())/12*(1+Assumptions!$F$11) -> 25000 | E42: =VLOOKUP($A$32,Assumptions!$A$35:$C$40,3,FALSE())/12*(1+Assumptions!$F$11) -> 25000 | F42: =VLOOKUP($A$32,Assumptions!$A$35:$C$40,3,FALSE())/12*(1+Assumptions!$F$11) -> 25000 | G42: =VLOOKUP($A$32,Assumptions!$A$35:$C$40,3,FALSE())/12*(1+Assumptions!$F$11) -> 25000 | H42: =VLOOKUP($A$32,Assumptions!$A$35:$C$40,3,FALSE())/12*(1+Assumptions!$F$11) -> 25000 | I42: =VLOOKUP($A$32,Assumptions!$A$35:$C$40,3,FALSE())/12*(1+Assumptions!$F$11) -> 25000 | ... M42: =VLOOKUP($A$32,Assumptions!$A$35:$C$40,3,FALSE())/12*(1+Assumptions!$F$11) -> 25000 | N42: =SUM(B42:M42) -> 300000
A43: Total operating expense | B43: =SUM(B34:B42) -> 193120.93 | C43: =SUM(C34:C42) -> 193120.93 | D43: =SUM(D34:D42) -> 220611.6 | E43: =SUM(E34:E42) -> 210151.83 | F43: =SUM(F34:F42) -> 210151.83 | G43: =SUM(G34:G42) -> 237908.63 | H43: =SUM(H34:H42) -> 238532.35 | I43: =SUM(I34:I42) -> 223082.35 | ... M43: =SUM(M34:M42) -> 223082.35 | N43: =SUM(B43:M43) -> 2619009.9
A45: Marketing
A46: FTE (average for the month) | B46: =SUMIF('Headcount Calc'!$B$6:$B$83,$A$45,'Headcount Calc'!K$6:K$83) -> 6 | C46: =SUMIF('Headcount Calc'!$B$6:$B$83,$A$45,'Headcount Calc'!L$6:L$83) -> 6 | D46: =SUMIF('Headcount Calc'!$B$6:$B$83,$A$45,'Headcount Calc'!M$6:M$83) -> 6 | E46: =SUMIF('Headcount Calc'!$B$6:$B$83,$A$45,'Headcount Calc'!N$6:N$83) -> 7 | F46: =SUMIF('Headcount Calc'!$B$6:$B$83,$A$45,'Headcount Calc'!O$6:O$83) -> 7 | G46: =SUMIF('Headcount Calc'!$B$6:$B$83,$A$45,'Headcount Calc'!P$6:P$83) -> 7 | H46: =SUMIF('Headcount Calc'!$B$6:$B$83,$A$45,'Headcount Calc'!Q$6:Q$83) -> 7 | I46: =SUMIF('Headcount Calc'!$B$6:$B$83,$A$45,'Headcount Calc'!R$6:R$83) -> 7 | ... M46: =SUMIF('Headcount Calc'!$B$6:$B$83,$A$45,'Headcount Calc'!V$6:V$83) -> 7 | N46: =AVERAGE(B46:M46) -> 6.75
A47: Salaries | B47: =SUMIF('Headcount Calc'!$B$6:$B$83,$A$45,'Headcount Calc'!W$6:W$83) -> 57166.667 | C47: =SUMIF('Headcount Calc'!$B$6:$B$83,$A$45,'Headcount Calc'!X$6:X$83) -> 57166.667 | D47: =SUMIF('Headcount Calc'!$B$6:$B$83,$A$45,'Headcount Calc'!Y$6:Y$83) -> 57166.667 | E47: =SUMIF('Headcount Calc'!$B$6:$B$83,$A$45,'Headcount Calc'!Z$6:Z$83) -> 66625.833 | F47: =SUMIF('Headcount Calc'!$B$6:$B$83,$A$45,'Headcount Calc'!AA$6:AA$83) -> 66625.833 | G47: =SUMIF('Headcount Calc'!$B$6:$B$83,$A$45,'Headcount Calc'!AB$6:AB$83) -> 66625.833 | H47: =SUMIF('Headcount Calc'!$B$6:$B$83,$A$45,'Headcount Calc'!AC$6:AC$83) -> 66625.833 | I47: =SUMIF('Headcount Calc'!$B$6:$B$83,$A$45,'Headcount Calc'!AD$6:AD$83) -> 66625.833 | ... M47: =SUMIF('Headcount Calc'!$B$6:$B$83,$A$45,'Headcount Calc'!AH$6:AH$83) -> 66625.833 | N47: =SUM(B47:M47) -> 771132.5
A48: Bonus & variable compensation | B48: =SUMPRODUCT(('Headcount Calc'!$B$6:$B$83=$A$45)*'Headcount Calc'!W$6:W$83*'Headcount Calc'!$I$6:$I$83) -> 7287.5 | C48: =SUMPRODUCT(('Headcount Calc'!$B$6:$B$83=$A$45)*'Headcount Calc'!X$6:X$83*'Headcount Calc'!$I$6:$I$83) -> 7287.5 | D48: =SUMPRODUCT(('Headcount Calc'!$B$6:$B$83=$A$45)*'Headcount Calc'!Y$6:Y$83*'Headcount Calc'!$I$6:$I$83) -> 7287.5 | E48: =SUMPRODUCT(('Headcount Calc'!$B$6:$B$83=$A$45)*'Headcount Calc'!Z$6:Z$83*'Headcount Calc'!$I$6:$I$83) -> 8139.2292 | F48: =SUMPRODUCT(('Headcount Calc'!$B$6:$B$83=$A$45)*'Headcount Calc'!AA$6:AA$83*'Headcount Calc'!$I$6:$I$83) -> 8139.2292 | G48: =SUMPRODUCT(('Headcount Calc'!$B$6:$B$83=$A$45)*'Headcount Calc'!AB$6:AB$83*'Headcount Calc'!$I$6:$I$83) -> 8139.2292 | H48: =SUMPRODUCT(('Headcount Calc'!$B$6:$B$83=$A$45)*'Headcount Calc'!AC$6:AC$83*'Headcount Calc'!$I$6:$I$83) -> 8139.2292 | I48: =SUMPRODUCT(('Headcount Calc'!$B$6:$B$83=$A$45)*'Headcount Calc'!AD$6:AD$83*'Headcount Calc'!$I$6:$I$83) -> 8139.2292 | ... M48: =SUMPRODUCT(('Headcount Calc'!$B$6:$B$83=$A$45)*'Headcount Calc'!AH$6:AH$83*'Headcount Calc'!$I$6:$I$83) -> 8139.2292 | N48: =SUM(B48:M48) -> 95115.562
A49: Payroll taxes | B49: =(B47+B48)*Assumptions!$B$15 -> 4640.7 | C49: =(C47+C48)*Assumptions!$B$15 -> 4640.7 | D49: =(D47+D48)*Assumptions!$B$15 -> 4640.7 | E49: =(E47+E48)*Assumptions!$B$15 -> 5383.0845 | F49: =(F47+F48)*Assumptions!$B$15 -> 5383.0845 | G49: =(G47+G48)*Assumptions!$B$15 -> 5383.0845 | H49: =(H47+H48)*Assumptions!$B$15 -> 5383.0845 | I49: =(I47+I48)*Assumptions!$B$15 -> 5383.0845 | ... M49: =(M47+M48)*Assumptions!$B$15 -> 5383.0845 | N49: =SUM(B49:M49) -> 62369.861
A50: Benefits | B50: =B46*Assumptions!$B$16 -> 6900 | C50: =C46*Assumptions!$B$16 -> 6900 | D50: =D46*Assumptions!$B$16 -> 6900 | E50: =E46*Assumptions!$B$16 -> 8050 | F50: =F46*Assumptions!$B$16 -> 8050 | G50: =G46*Assumptions!$B$16 -> 8050 | H50: =H46*Assumptions!$B$16 -> 8050 | I50: =I46*Assumptions!$B$16 -> 8050 | ... M50: =M46*Assumptions!$B$16 -> 8050 | N50: =SUM(B50:M50) -> 93150
A51: Recruiting & onboarding | B51: =SUMPRODUCT(('Headcount Calc'!$B$6:$B$83=$A$45)*('Headcount Calc'!$C$6:$C$83="Open role")*('Headcount Calc'!$H$6:$H$83=1)*('Headcount Calc'!$F$6:$F$83>=B$4)*('Headcount Calc'!$F$6:$F$83<=EOMONTH(B$4,0))*'Headcount Calc'!$E$6:$E$83)*Assumptions!$B$19+SUMPRODUCT(('Headcount Calc'!$B$6:$B$83=$A$45)*('Headcount Calc'!$C$6:$C$83="Open role")*('Headcount Calc'!$H$6:$H$83=1)*('Headcount Calc'!$F$6:$F$83>=B$4)*('Headcount Calc'!$F$6:$F$83<=EOMONTH(B$4,0)))*Assumptions!$B$20 -> 0 | C51: =SUMPRODUCT(('Headcount Calc'!$B$6:$B$83=$A$45)*('Headcount Calc'!$C$6:$C$83="Open role")*('Headcount Calc'!$H$6:$H$83=1)*('Headcount Calc'!$F$6:$F$83>=C$4)*('Headcount Calc'!$F$6:$F$83<=EOMONTH(C$4,0))*'Headcount Calc'!$E$6:$E$83)*Assumptions!$B$19+SUMPRODUCT(('Headcount Calc'!$B$6:$B$83=$A$45)*('Headcount Calc'!$C$6:$C$83="Open role")*('Headcount Calc'!$H$6:$H$83=1)*('Headcount Calc'!$F$6:$F$83>=C$4)*('Headcount Calc'!$F$6:$F$83<=EOMONTH(C$4,0)))*Assumptions!$B$20 -> 0 | D51: =SUMPRODUCT(('Headcount Calc'!$B$6:$B$83=$A$45)*('Headcount Calc'!$C$6:$C$83="Open role")*('Headcount Calc'!$H$6:$H$83=1)*('Headcount Calc'!$F$6:$F$83>=D$4)*('Headcount Calc'!$F$6:$F$83<=EOMONTH(D$4,0))*'Headcount Calc'!$E$6:$E$83)*Assumptions!$B$19+SUMPRODUCT(('Headcount Calc'!$B$6:$B$83=$A$45)*('Headcount Calc'!$C$6:$C$83="Open role")*('Headcount Calc'!$H$6:$H$83=1)*('Headcount Calc'!$F$6:$F$83>=D$4)*('Headcount Calc'!$F$6:$F$83<=EOMONTH(D$4,0)))*Assumptions!$B$20 -> 0 | E51: =SUMPRODUCT(('Headcount Calc'!$B$6:$B$83=$A$45)*('Headcount Calc'!$C$6:$C$83="Open role")*('Headcount Calc'!$H$6:$H$83=1)*('Headcount Calc'!$F$6:$F$83>=E$4)*('Headcount Calc'!$F$6:$F$83<=EOMONTH(E$4,0))*'Headcount Calc'!$E$6:$E$83)*Assumptions!$B$19+SUMPRODUCT(('Headcount Calc'!$B$6:$B$83=$A$45)*('Headcount Calc'!$C$6:$C$83="Open role")*('Headcount Calc'!$H$6:$H$83=1)*('Headcount Calc'!$F$6:$F$83>=E$4)*('Headcount Calc'!$F$6:$F$83<=EOMONTH(E$4,0)))*Assumptions!$B$20 -> 16425 | F51: =SUMPRODUCT(('Headcount Calc'!$B$6:$B$83=$A$45)*('Headcount Calc'!$C$6:$C$83="Open role")*('Headcount Calc'!$H$6:$H$83=1)*('Headcount Calc'!$F$6:$F$83>=F$4)*('Headcount Calc'!$F$6:$F$83<=EOMONTH(F$4,0))*'Headcount Calc'!$E$6:$E$83)*Assumptions!$B$19+SUMPRODUCT(('Headcount Calc'!$B$6:$B$83=$A$45)*('Headcount Calc'!$C$6:$C$83="Open role")*('Headcount Calc'!$H$6:$H$83=1)*('Headcount Calc'!$F$6:$F$83>=F$4)*('Headcount Calc'!$F$6:$F$83<=EOMONTH(F$4,0)))*Assumptions!$B$20 -> 0 | G51: =SUMPRODUCT(('Headcount Calc'!$B$6:$B$83=$A$45)*('Headcount Calc'!$C$6:$C$83="Open role")*('Headcount Calc'!$H$6:$H$83=1)*('Headcount Calc'!$F$6:$F$83>=G$4)*('Headcount Calc'!$F$6:$F$83<=EOMONTH(G$4,0))*'Headcount Calc'!$E$6:$E$83)*Assumptions!$B$19+SUMPRODUCT(('Headcount Calc'!$B$6:$B$83=$A$45)*('Headcount Calc'!$C$6:$C$83="Open role")*('Headcount Calc'!$H$6:$H$83=1)*('Headcount Calc'!$F$6:$F$83>=G$4)*('Headcount Calc'!$F$6:$F$83<=EOMONTH(G$4,0)))*Assumptions!$B$20 -> 0 | H51: =SUMPRODUCT(('Headcount Calc'!$B$6:$B$83=$A$45)*('Headcount Calc'!$C$6:$C$83="Open role")*('Headcount Calc'!$H$6:$H$83=1)*('Headcount Calc'!$F$6:$F$83>=H$4)*('Headcount Calc'!$F$6:$F$83<=EOMONTH(H$4,0))*'Headcount Calc'!$E$6:$E$83)*Assumptions!$B$19+SUMPRODUCT(('Headcount Calc'!$B$6:$B$83=$A$45)*('Headcount Calc'!$C$6:$C$83="Open role")*('Headcount Calc'!$H$6:$H$83=1)*('Headcount Calc'!$F$6:$F$83>=H$4)*('Headcount Calc'!$F$6:$F$83<=EOMONTH(H$4,0)))*Assumptions!$B$20 -> 0 | I51: =SUMPRODUCT(('Headcount Calc'!$B$6:$B$83=$A$45)*('Headcount Calc'!$C$6:$C$83="Open role")*('Headcount Calc'!$H$6:$H$83=1)*('Headcount Calc'!$F$6:$F$83>=I$4)*('Headcount Calc'!$F$6:$F$83<=EOMONTH(I$4,0))*'Headcount Calc'!$E$6:$E$83)*Assumptions!$B$19+SUMPRODUCT(('Headcount Calc'!$B$6:$B$83=$A$45)*('Headcount Calc'!$C$6:$C$83="Open role")*('Headcount Calc'!$H$6:$H$83=1)*('Headcount Calc'!$F$6:$F$83>=I$4)*('Headcount Calc'!$F$6:$F$83<=EOMONTH(I$4,0)))*Assumptions!$B$20 -> 0 | ... M51: =SUMPRODUCT(('Headcount Calc'!$B$6:$B$83=$A$45)*('Headcount Calc'!$C$6:$C$83="Open role")*('Headcount Calc'!$H$6:$H$83=1)*('Headcount Calc'!$F$6:$F$83>=M$4)*('Headcount Calc'!$F$6:$F$83<=EOMONTH(M$4,0))*'Headcount Calc'!$E$6:$E$83)*Assumptions!$B$19+SUMPRODUCT(('Headcount Calc'!$B$6:$B$83=$A$45)*('Headcount Calc'!$C$6:$C$83="Open role")*('Headcount Calc'!$H$6:$H$83=1)*('Headcount Calc'!$F$6:$F$83>=M$4)*('Headcount Calc'!$F$6:$F$83<=EOMONTH(M$4,0)))*Assumptions!$B$20 -> 0 | N51: =SUM(B51:M51) -> 16425
A52: Software & tools | B52: =B46*Assumptions!$B$21 -> 1500 | C52: =C46*Assumptions!$B$21 -> 1500 | D52: =D46*Assumptions!$B$21 -> 1500 | E52: =E46*Assumptions!$B$21 -> 1750 | F52: =F46*Assumptions!$B$21 -> 1750 | G52: =G46*Assumptions!$B$21 -> 1750 | H52: =H46*Assumptions!$B$21 -> 1750 | I52: =I46*Assumptions!$B$21 -> 1750 | ... M52: =M46*Assumptions!$B$21 -> 1750 | N52: =SUM(B52:M52) -> 20250
A53: Travel & entertainment | B53: =B46*VLOOKUP($A$45,Assumptions!$A$35:$C$40,2,FALSE()) -> 2400 | C53: =C46*VLOOKUP($A$45,Assumptions!$A$35:$C$40,2,FALSE()) -> 2400 | D53: =D46*VLOOKUP($A$45,Assumptions!$A$35:$C$40,2,FALSE()) -> 2400 | E53: =E46*VLOOKUP($A$45,Assumptions!$A$35:$C$40,2,FALSE()) -> 2800 | F53: =F46*VLOOKUP($A$45,Assumptions!$A$35:$C$40,2,FALSE()) -> 2800 | G53: =G46*VLOOKUP($A$45,Assumptions!$A$35:$C$40,2,FALSE()) -> 2800 | H53: =H46*VLOOKUP($A$45,Assumptions!$A$35:$C$40,2,FALSE()) -> 2800 | I53: =I46*VLOOKUP($A$45,Assumptions!$A$35:$C$40,2,FALSE()) -> 2800 | ... M53: =M46*VLOOKUP($A$45,Assumptions!$A$35:$C$40,2,FALSE()) -> 2800 | N53: =SUM(B53:M53) -> 32400
A54: Facilities | B54: =B46*Assumptions!$B$22 -> 3600 | C54: =C46*Assumptions!$B$22 -> 3600 | D54: =D46*Assumptions!$B$22 -> 3600 | E54: =E46*Assumptions!$B$22 -> 4200 | F54: =F46*Assumptions!$B$22 -> 4200 | G54: =G46*Assumptions!$B$22 -> 4200 | H54: =H46*Assumptions!$B$22 -> 4200 | I54: =I46*Assumptions!$B$22 -> 4200 | ... M54: =M46*Assumptions!$B$22 -> 4200 | N54: =SUM(B54:M54) -> 48600
A55: Programs & vendors | B55: =VLOOKUP($A$45,Assumptions!$A$35:$C$40,3,FALSE())/12*(1+Assumptions!$F$11) -> 116666.67 | C55: =VLOOKUP($A$45,Assumptions!$A$35:$C$40,3,FALSE())/12*(1+Assumptions!$F$11) -> 116666.67 | D55: =VLOOKUP($A$45,Assumptions!$A$35:$C$40,3,FALSE())/12*(1+Assumptions!$F$11) -> 116666.67 | E55: =VLOOKUP($A$45,Assumptions!$A$35:$C$40,3,FALSE())/12*(1+Assumptions!$F$11) -> 116666.67 | F55: =VLOOKUP($A$45,Assumptions!$A$35:$C$40,3,FALSE())/12*(1+Assumptions!$F$11) -> 116666.67 | G55: =VLOOKUP($A$45,Assumptions!$A$35:$C$40,3,FALSE())/12*(1+Assumptions!$F$11) -> 116666.67 | H55: =VLOOKUP($A$45,Assumptions!$A$35:$C$40,3,FALSE())/12*(1+Assumptions!$F$11) -> 116666.67 | I55: =VLOOKUP($A$45,Assumptions!$A$35:$C$40,3,FALSE())/12*(1+Assumptions!$F$11) -> 116666.67 | ... M55: =VLOOKUP($A$45,Assumptions!$A$35:$C$40,3,FALSE())/12*(1+Assumptions!$F$11) -> 116666.67 | N55: =SUM(B55:M55) -> 1400000
A56: Total operating expense | B56: =SUM(B47:B55) -> 200161.53 | C56: =SUM(C47:C55) -> 200161.53 | D56: =SUM(D47:D55) -> 200161.53 | E56: =SUM(E47:E55) -> 230039.81 | F56: =SUM(F47:F55) -> 213614.81 | G56: =SUM(G47:G55) -> 213614.81 | H56: =SUM(H47:H55) -> 213614.81 | I56: =SUM(I47:I55) -> 213614.81 | ... M56: =SUM(M47:M55) -> 213614.81 | N56: =SUM(B56:M56) -> 2539442.9
A58: Customer Success
A59: FTE (average for the month) | B59: =SUMIF('Headcount Calc'!$B$6:$B$83,$A$58,'Headcount Calc'!K$6:K$83) -> 9 | C59: =SUMIF('Headcount Calc'!$B$6:$B$83,$A$58,'Headcount Calc'!L$6:L$83) -> 9 | D59: =SUMIF('Headcount Calc'!$B$6:$B$83,$A$58,'Headcount Calc'!M$6:M$83) -> 9 | E59: =SUMIF('Headcount Calc'!$B$6:$B$83,$A$58,'Headcount Calc'!N$6:N$83) -> 9 | F59: =SUMIF('Headcount Calc'!$B$6:$B$83,$A$58,'Headcount Calc'!O$6:O$83) -> 10 | G59: =SUMIF('Headcount Calc'!$B$6:$B$83,$A$58,'Headcount Calc'!P$6:P$83) -> 10 | H59: =SUMIF('Headcount Calc'!$B$6:$B$83,$A$58,'Headcount Calc'!Q$6:Q$83) -> 10 | I59: =SUMIF('Headcount Calc'!$B$6:$B$83,$A$58,'Headcount Calc'!R$6:R$83) -> 10 | ... M59: =SUMIF('Headcount Calc'!$B$6:$B$83,$A$58,'Headcount Calc'!V$6:V$83) -> 10 | N59: =AVERAGE(B59:M59) -> 9.6666667
A60: Salaries | B60: =SUMIF('Headcount Calc'!$B$6:$B$83,$A$58,'Headcount Calc'!W$6:W$83) -> 61500 | C60: =SUMIF('Headcount Calc'!$B$6:$B$83,$A$58,'Headcount Calc'!X$6:X$83) -> 61500 | D60: =SUMIF('Headcount Calc'!$B$6:$B$83,$A$58,'Headcount Calc'!Y$6:Y$83) -> 61500 | E60: =SUMIF('Headcount Calc'!$B$6:$B$83,$A$58,'Headcount Calc'!Z$6:Z$83) -> 63652.5 | F60: =SUMIF('Headcount Calc'!$B$6:$B$83,$A$58,'Headcount Calc'!AA$6:AA$83) -> 70319.167 | G60: =SUMIF('Headcount Calc'!$B$6:$B$83,$A$58,'Headcount Calc'!AB$6:AB$83) -> 70319.167 | H60: =SUMIF('Headcount Calc'!$B$6:$B$83,$A$58,'Headcount Calc'!AC$6:AC$83) -> 70319.167 | I60: =SUMIF('Headcount Calc'!$B$6:$B$83,$A$58,'Headcount Calc'!AD$6:AD$83) -> 70319.167 | ... M60: =SUMIF('Headcount Calc'!$B$6:$B$83,$A$58,'Headcount Calc'!AH$6:AH$83) -> 70351.042 | N60: =SUM(B60:M60) -> 810833.33
A61: Bonus & variable compensation | B61: =SUMPRODUCT(('Headcount Calc'!$B$6:$B$83=$A$58)*'Headcount Calc'!W$6:W$83*'Headcount Calc'!$I$6:$I$83) -> 5303.3333 | C61: =SUMPRODUCT(('Headcount Calc'!$B$6:$B$83=$A$58)*'Headcount Calc'!X$6:X$83*'Headcount Calc'!$I$6:$I$83) -> 5303.3333 | D61: =SUMPRODUCT(('Headcount Calc'!$B$6:$B$83=$A$58)*'Headcount Calc'!Y$6:Y$83*'Headcount Calc'!$I$6:$I$83) -> 5303.3333 | E61: =SUMPRODUCT(('Headcount Calc'!$B$6:$B$83=$A$58)*'Headcount Calc'!Z$6:Z$83*'Headcount Calc'!$I$6:$I$83) -> 5488.95 | F61: =SUMPRODUCT(('Headcount Calc'!$B$6:$B$83=$A$58)*'Headcount Calc'!AA$6:AA$83*'Headcount Calc'!$I$6:$I$83) -> 6022.2833 | G61: =SUMPRODUCT(('Headcount Calc'!$B$6:$B$83=$A$58)*'Headcount Calc'!AB$6:AB$83*'Headcount Calc'!$I$6:$I$83) -> 6022.2833 | H61: =SUMPRODUCT(('Headcount Calc'!$B$6:$B$83=$A$58)*'Headcount Calc'!AC$6:AC$83*'Headcount Calc'!$I$6:$I$83) -> 6022.2833 | I61: =SUMPRODUCT(('Headcount Calc'!$B$6:$B$83=$A$58)*'Headcount Calc'!AD$6:AD$83*'Headcount Calc'!$I$6:$I$83) -> 6022.2833 | ... M61: =SUMPRODUCT(('Headcount Calc'!$B$6:$B$83=$A$58)*'Headcount Calc'!AH$6:AH$83*'Headcount Calc'!$I$6:$I$83) -> 6023.8771 | N61: =SUM(B61:M61) -> 69583.592
A62: Payroll taxes | B62: =(B60+B61)*Assumptions!$B$15 -> 4809.84 | C62: =(C60+C61)*Assumptions!$B$15 -> 4809.84 | D62: =(D60+D61)*Assumptions!$B$15 -> 4809.84 | E62: =(E60+E61)*Assumptions!$B$15 -> 4978.1844 | F62: =(F60+F61)*Assumptions!$B$15 -> 5496.5844 | G62: =(G60+G61)*Assumptions!$B$15 -> 5496.5844 | H62: =(H60+H61)*Assumptions!$B$15 -> 5496.5844 | I62: =(I60+I61)*Assumptions!$B$15 -> 5496.5844 | ... M62: =(M60+M61)*Assumptions!$B$15 -> 5498.9942 | N62: =SUM(B62:M62) -> 63390.019
A63: Benefits | B63: =B59*Assumptions!$B$16 -> 10350 | C63: =C59*Assumptions!$B$16 -> 10350 | D63: =D59*Assumptions!$B$16 -> 10350 | E63: =E59*Assumptions!$B$16 -> 10350 | F63: =F59*Assumptions!$B$16 -> 11500 | G63: =G59*Assumptions!$B$16 -> 11500 | H63: =H59*Assumptions!$B$16 -> 11500 | I63: =I59*Assumptions!$B$16 -> 11500 | ... M63: =M59*Assumptions!$B$16 -> 11500 | N63: =SUM(B63:M63) -> 133400
A64: Recruiting & onboarding | B64: =SUMPRODUCT(('Headcount Calc'!$B$6:$B$83=$A$58)*('Headcount Calc'!$C$6:$C$83="Open role")*('Headcount Calc'!$H$6:$H$83=1)*('Headcount Calc'!$F$6:$F$83>=B$4)*('Headcount Calc'!$F$6:$F$83<=EOMONTH(B$4,0))*'Headcount Calc'!$E$6:$E$83)*Assumptions!$B$19+SUMPRODUCT(('Headcount Calc'!$B$6:$B$83=$A$58)*('Headcount Calc'!$C$6:$C$83="Open role")*('Headcount Calc'!$H$6:$H$83=1)*('Headcount Calc'!$F$6:$F$83>=B$4)*('Headcount Calc'!$F$6:$F$83<=EOMONTH(B$4,0)))*Assumptions!$B$20 -> 0 | C64: =SUMPRODUCT(('Headcount Calc'!$B$6:$B$83=$A$58)*('Headcount Calc'!$C$6:$C$83="Open role")*('Headcount Calc'!$H$6:$H$83=1)*('Headcount Calc'!$F$6:$F$83>=C$4)*('Headcount Calc'!$F$6:$F$83<=EOMONTH(C$4,0))*'Headcount Calc'!$E$6:$E$83)*Assumptions!$B$19+SUMPRODUCT(('Headcount Calc'!$B$6:$B$83=$A$58)*('Headcount Calc'!$C$6:$C$83="Open role")*('Headcount Calc'!$H$6:$H$83=1)*('Headcount Calc'!$F$6:$F$83>=C$4)*('Headcount Calc'!$F$6:$F$83<=EOMONTH(C$4,0)))*Assumptions!$B$20 -> 0 | D64: =SUMPRODUCT(('Headcount Calc'!$B$6:$B$83=$A$58)*('Headcount Calc'!$C$6:$C$83="Open role")*('Headcount Calc'!$H$6:$H$83=1)*('Headcount Calc'!$F$6:$F$83>=D$4)*('Headcount Calc'!$F$6:$F$83<=EOMONTH(D$4,0))*'Headcount Calc'!$E$6:$E$83)*Assumptions!$B$19+SUMPRODUCT(('Headcount Calc'!$B$6:$B$83=$A$58)*('Headcount Calc'!$C$6:$C$83="Open role")*('Headcount Calc'!$H$6:$H$83=1)*('Headcount Calc'!$F$6:$F$83>=D$4)*('Headcount Calc'!$F$6:$F$83<=EOMONTH(D$4,0)))*Assumptions!$B$20 -> 0 | E64: =SUMPRODUCT(('Headcount Calc'!$B$6:$B$83=$A$58)*('Headcount Calc'!$C$6:$C$83="Open role")*('Headcount Calc'!$H$6:$H$83=1)*('Headcount Calc'!$F$6:$F$83>=E$4)*('Headcount Calc'!$F$6:$F$83<=EOMONTH(E$4,0))*'Headcount Calc'!$E$6:$E$83)*Assumptions!$B$19+SUMPRODUCT(('Headcount Calc'!$B$6:$B$83=$A$58)*('Headcount Calc'!$C$6:$C$83="Open role")*('Headcount Calc'!$H$6:$H$83=1)*('Headcount Calc'!$F$6:$F$83>=E$4)*('Headcount Calc'!$F$6:$F$83<=EOMONTH(E$4,0)))*Assumptions!$B$20 -> 0 | F64: =SUMPRODUCT(('Headcount Calc'!$B$6:$B$83=$A$58)*('Headcount Calc'!$C$6:$C$83="Open role")*('Headcount Calc'!$H$6:$H$83=1)*('Headcount Calc'!$F$6:$F$83>=F$4)*('Headcount Calc'!$F$6:$F$83<=EOMONTH(F$4,0))*'Headcount Calc'!$E$6:$E$83)*Assumptions!$B$19+SUMPRODUCT(('Headcount Calc'!$B$6:$B$83=$A$58)*('Headcount Calc'!$C$6:$C$83="Open role")*('Headcount Calc'!$H$6:$H$83=1)*('Headcount Calc'!$F$6:$F$83>=F$4)*('Headcount Calc'!$F$6:$F$83<=EOMONTH(F$4,0)))*Assumptions!$B$20 -> 15000 | G64: =SUMPRODUCT(('Headcount Calc'!$B$6:$B$83=$A$58)*('Headcount Calc'!$C$6:$C$83="Open role")*('Headcount Calc'!$H$6:$H$83=1)*('Headcount Calc'!$F$6:$F$83>=G$4)*('Headcount Calc'!$F$6:$F$83<=EOMONTH(G$4,0))*'Headcount Calc'!$E$6:$E$83)*Assumptions!$B$19+SUMPRODUCT(('Headcount Calc'!$B$6:$B$83=$A$58)*('Headcount Calc'!$C$6:$C$83="Open role")*('Headcount Calc'!$H$6:$H$83=1)*('Headcount Calc'!$F$6:$F$83>=G$4)*('Headcount Calc'!$F$6:$F$83<=EOMONTH(G$4,0)))*Assumptions!$B$20 -> 0 | H64: =SUMPRODUCT(('Headcount Calc'!$B$6:$B$83=$A$58)*('Headcount Calc'!$C$6:$C$83="Open role")*('Headcount Calc'!$H$6:$H$83=1)*('Headcount Calc'!$F$6:$F$83>=H$4)*('Headcount Calc'!$F$6:$F$83<=EOMONTH(H$4,0))*'Headcount Calc'!$E$6:$E$83)*Assumptions!$B$19+SUMPRODUCT(('Headcount Calc'!$B$6:$B$83=$A$58)*('Headcount Calc'!$C$6:$C$83="Open role")*('Headcount Calc'!$H$6:$H$83=1)*('Headcount Calc'!$F$6:$F$83>=H$4)*('Headcount Calc'!$F$6:$F$83<=EOMONTH(H$4,0)))*Assumptions!$B$20 -> 0 | I64: =SUMPRODUCT(('Headcount Calc'!$B$6:$B$83=$A$58)*('Headcount Calc'!$C$6:$C$83="Open role")*('Headcount Calc'!$H$6:$H$83=1)*('Headcount Calc'!$F$6:$F$83>=I$4)*('Headcount Calc'!$F$6:$F$83<=EOMONTH(I$4,0))*'Headcount Calc'!$E$6:$E$83)*Assumptions!$B$19+SUMPRODUCT(('Headcount Calc'!$B$6:$B$83=$A$58)*('Headcount Calc'!$C$6:$C$83="Open role")*('Headcount Calc'!$H$6:$H$83=1)*('Headcount Calc'!$F$6:$F$83>=I$4)*('Headcount Calc'!$F$6:$F$83<=EOMONTH(I$4,0)))*Assumptions!$B$20 -> 0 | ... M64: =SUMPRODUCT(('Headcount Calc'!$B$6:$B$83=$A$58)*('Headcount Calc'!$C$6:$C$83="Open role")*('Headcount Calc'!$H$6:$H$83=1)*('Headcount Calc'!$F$6:$F$83>=M$4)*('Headcount Calc'!$F$6:$F$83<=EOMONTH(M$4,0))*'Headcount Calc'!$E$6:$E$83)*Assumptions!$B$19+SUMPRODUCT(('Headcount Calc'!$B$6:$B$83=$A$58)*('Headcount Calc'!$C$6:$C$83="Open role")*('Headcount Calc'!$H$6:$H$83=1)*('Headcount Calc'!$F$6:$F$83>=M$4)*('Headcount Calc'!$F$6:$F$83<=EOMONTH(M$4,0)))*Assumptions!$B$20 -> 0 | N64: =SUM(B64:M64) -> 27450
A65: Software & tools | B65: =B59*Assumptions!$B$21 -> 2250 | C65: =C59*Assumptions!$B$21 -> 2250 | D65: =D59*Assumptions!$B$21 -> 2250 | E65: =E59*Assumptions!$B$21 -> 2250 | F65: =F59*Assumptions!$B$21 -> 2500 | G65: =G59*Assumptions!$B$21 -> 2500 | H65: =H59*Assumptions!$B$21 -> 2500 | I65: =I59*Assumptions!$B$21 -> 2500 | ... M65: =M59*Assumptions!$B$21 -> 2500 | N65: =SUM(B65:M65) -> 29000
A66: Travel & entertainment | B66: =B59*VLOOKUP($A$58,Assumptions!$A$35:$C$40,2,FALSE()) -> 1800 | C66: =C59*VLOOKUP($A$58,Assumptions!$A$35:$C$40,2,FALSE()) -> 1800 | D66: =D59*VLOOKUP($A$58,Assumptions!$A$35:$C$40,2,FALSE()) -> 1800 | E66: =E59*VLOOKUP($A$58,Assumptions!$A$35:$C$40,2,FALSE()) -> 1800 | F66: =F59*VLOOKUP($A$58,Assumptions!$A$35:$C$40,2,FALSE()) -> 2000 | G66: =G59*VLOOKUP($A$58,Assumptions!$A$35:$C$40,2,FALSE()) -> 2000 | H66: =H59*VLOOKUP($A$58,Assumptions!$A$35:$C$40,2,FALSE()) -> 2000 | I66: =I59*VLOOKUP($A$58,Assumptions!$A$35:$C$40,2,FALSE()) -> 2000 | ... M66: =M59*VLOOKUP($A$58,Assumptions!$A$35:$C$40,2,FALSE()) -> 2000 | N66: =SUM(B66:M66) -> 23200
A67: Facilities | B67: =B59*Assumptions!$B$22 -> 5400 | C67: =C59*Assumptions!$B$22 -> 5400 | D67: =D59*Assumptions!$B$22 -> 5400 | E67: =E59*Assumptions!$B$22 -> 5400 | F67: =F59*Assumptions!$B$22 -> 6000 | G67: =G59*Assumptions!$B$22 -> 6000 | H67: =H59*Assumptions!$B$22 -> 6000 | I67: =I59*Assumptions!$B$22 -> 6000 | ... M67: =M59*Assumptions!$B$22 -> 6000 | N67: =SUM(B67:M67) -> 69600
A68: Programs & vendors | B68: =VLOOKUP($A$58,Assumptions!$A$35:$C$40,3,FALSE())/12*(1+Assumptions!$F$11) -> 12500 | C68: =VLOOKUP($A$58,Assumptions!$A$35:$C$40,3,FALSE())/12*(1+Assumptions!$F$11) -> 12500 | D68: =VLOOKUP($A$58,Assumptions!$A$35:$C$40,3,FALSE())/12*(1+Assumptions!$F$11) -> 12500 | E68: =VLOOKUP($A$58,Assumptions!$A$35:$C$40,3,FALSE())/12*(1+Assumptions!$F$11) -> 12500 | F68: =VLOOKUP($A$58,Assumptions!$A$35:$C$40,3,FALSE())/12*(1+Assumptions!$F$11) -> 12500 | G68: =VLOOKUP($A$58,Assumptions!$A$35:$C$40,3,FALSE())/12*(1+Assumptions!$F$11) -> 12500 | H68: =VLOOKUP($A$58,Assumptions!$A$35:$C$40,3,FALSE())/12*(1+Assumptions!$F$11) -> 12500 | I68: =VLOOKUP($A$58,Assumptions!$A$35:$C$40,3,FALSE())/12*(1+Assumptions!$F$11) -> 12500 | ... M68: =VLOOKUP($A$58,Assumptions!$A$35:$C$40,3,FALSE())/12*(1+Assumptions!$F$11) -> 12500 | N68: =SUM(B68:M68) -> 150000
A69: Total operating expense | B69: =SUM(B60:B68) -> 103913.17 | C69: =SUM(C60:C68) -> 103913.17 | D69: =SUM(D60:D68) -> 103913.17 | E69: =SUM(E60:E68) -> 106419.63 | F69: =SUM(F60:F68) -> 131338.03 | G69: =SUM(G60:G68) -> 116338.03 | H69: =SUM(H60:H68) -> 116338.03 | I69: =SUM(I60:I68) -> 116338.03 | ... M69: =SUM(M60:M68) -> 116373.91 | N69: =SUM(B69:M69) -> 1376456.9
A71: G&A
A72: FTE (average for the month) | B72: =SUMIF('Headcount Calc'!$B$6:$B$83,$A$71,'Headcount Calc'!K$6:K$83) -> 8 | C72: =SUMIF('Headcount Calc'!$B$6:$B$83,$A$71,'Headcount Calc'!L$6:L$83) -> 9 | D72: =SUMIF('Headcount Calc'!$B$6:$B$83,$A$71,'Headcount Calc'!M$6:M$83) -> 9 | E72: =SUMIF('Headcount Calc'!$B$6:$B$83,$A$71,'Headcount Calc'!N$6:N$83) -> 9 | F72: =SUMIF('Headcount Calc'!$B$6:$B$83,$A$71,'Headcount Calc'!O$6:O$83) -> 9 | G72: =SUMIF('Headcount Calc'!$B$6:$B$83,$A$71,'Headcount Calc'!P$6:P$83) -> 10 | H72: =SUMIF('Headcount Calc'!$B$6:$B$83,$A$71,'Headcount Calc'!Q$6:Q$83) -> 10 | I72: =SUMIF('Headcount Calc'!$B$6:$B$83,$A$71,'Headcount Calc'!R$6:R$83) -> 10 | ... M72: =SUMIF('Headcount Calc'!$B$6:$B$83,$A$71,'Headcount Calc'!V$6:V$83) -> 10 | N72: =AVERAGE(B72:M72) -> 9.5
A73: Salaries | B73: =SUMIF('Headcount Calc'!$B$6:$B$83,$A$71,'Headcount Calc'!W$6:W$83) -> 77583.333 | C73: =SUMIF('Headcount Calc'!$B$6:$B$83,$A$71,'Headcount Calc'!X$6:X$83) -> 87625 | D73: =SUMIF('Headcount Calc'!$B$6:$B$83,$A$71,'Headcount Calc'!Y$6:Y$83) -> 87625 | E73: =SUMIF('Headcount Calc'!$B$6:$B$83,$A$71,'Headcount Calc'!Z$6:Z$83) -> 90340.417 | F73: =SUMIF('Headcount Calc'!$B$6:$B$83,$A$71,'Headcount Calc'!AA$6:AA$83) -> 90340.417 | G73: =SUMIF('Headcount Calc'!$B$6:$B$83,$A$71,'Headcount Calc'!AB$6:AB$83) -> 98090.417 | H73: =SUMIF('Headcount Calc'!$B$6:$B$83,$A$71,'Headcount Calc'!AC$6:AC$83) -> 98090.417 | I73: =SUMIF('Headcount Calc'!$B$6:$B$83,$A$71,'Headcount Calc'!AD$6:AD$83) -> 98090.417 | ... M73: =SUMIF('Headcount Calc'!$B$6:$B$83,$A$71,'Headcount Calc'!AH$6:AH$83) -> 98090.417 | N73: =SUM(B73:M73) -> 1120147.1
A74: Bonus & variable compensation | B74: =SUMPRODUCT(('Headcount Calc'!$B$6:$B$83=$A$71)*'Headcount Calc'!W$6:W$83*'Headcount Calc'!$I$6:$I$83) -> 9318.75 | C74: =SUMPRODUCT(('Headcount Calc'!$B$6:$B$83=$A$71)*'Headcount Calc'!X$6:X$83*'Headcount Calc'!$I$6:$I$83) -> 10322.917 | D74: =SUMPRODUCT(('Headcount Calc'!$B$6:$B$83=$A$71)*'Headcount Calc'!Y$6:Y$83*'Headcount Calc'!$I$6:$I$83) -> 10322.917 | E74: =SUMPRODUCT(('Headcount Calc'!$B$6:$B$83=$A$71)*'Headcount Calc'!Z$6:Z$83*'Headcount Calc'!$I$6:$I$83) -> 10649.073 | F74: =SUMPRODUCT(('Headcount Calc'!$B$6:$B$83=$A$71)*'Headcount Calc'!AA$6:AA$83*'Headcount Calc'!$I$6:$I$83) -> 10649.073 | G74: =SUMPRODUCT(('Headcount Calc'!$B$6:$B$83=$A$71)*'Headcount Calc'!AB$6:AB$83*'Headcount Calc'!$I$6:$I$83) -> 11269.073 | H74: =SUMPRODUCT(('Headcount Calc'!$B$6:$B$83=$A$71)*'Headcount Calc'!AC$6:AC$83*'Headcount Calc'!$I$6:$I$83) -> 11269.073 | I74: =SUMPRODUCT(('Headcount Calc'!$B$6:$B$83=$A$71)*'Headcount Calc'!AD$6:AD$83*'Headcount Calc'!$I$6:$I$83) -> 11269.073 | ... M74: =SUMPRODUCT(('Headcount Calc'!$B$6:$B$83=$A$71)*'Headcount Calc'!AH$6:AH$83*'Headcount Calc'!$I$6:$I$83) -> 11269.073 | N74: =SUM(B74:M74) -> 130146.24
A75: Payroll taxes | B75: =(B73+B74)*Assumptions!$B$15 -> 6256.95 | C75: =(C73+C74)*Assumptions!$B$15 -> 7052.25 | D75: =(D73+D74)*Assumptions!$B$15 -> 7052.25 | E75: =(E73+E74)*Assumptions!$B$15 -> 7271.2433 | F75: =(F73+F74)*Assumptions!$B$15 -> 7271.2433 | G75: =(G73+G74)*Assumptions!$B$15 -> 7873.8832 | H75: =(H73+H74)*Assumptions!$B$15 -> 7873.8832 | I75: =(I73+I74)*Assumptions!$B$15 -> 7873.8832 | ... M75: =(M73+M74)*Assumptions!$B$15 -> 7873.8832 | N75: =SUM(B75:M75) -> 90021.119
A76: Benefits | B76: =B72*Assumptions!$B$16 -> 9200 | C76: =C72*Assumptions!$B$16 -> 10350 | D76: =D72*Assumptions!$B$16 -> 10350 | E76: =E72*Assumptions!$B$16 -> 10350 | F76: =F72*Assumptions!$B$16 -> 10350 | G76: =G72*Assumptions!$B$16 -> 11500 | H76: =H72*Assumptions!$B$16 -> 11500 | I76: =I72*Assumptions!$B$16 -> 11500 | ... M76: =M72*Assumptions!$B$16 -> 11500 | N76: =SUM(B76:M76) -> 131100
A77: Recruiting & onboarding | B77: =SUMPRODUCT(('Headcount Calc'!$B$6:$B$83=$A$71)*('Headcount Calc'!$C$6:$C$83="Open role")*('Headcount Calc'!$H$6:$H$83=1)*('Headcount Calc'!$F$6:$F$83>=B$4)*('Headcount Calc'!$F$6:$F$83<=EOMONTH(B$4,0))*'Headcount Calc'!$E$6:$E$83)*Assumptions!$B$19+SUMPRODUCT(('Headcount Calc'!$B$6:$B$83=$A$71)*('Headcount Calc'!$C$6:$C$83="Open role")*('Headcount Calc'!$H$6:$H$83=1)*('Headcount Calc'!$F$6:$F$83>=B$4)*('Headcount Calc'!$F$6:$F$83<=EOMONTH(B$4,0)))*Assumptions!$B$20 -> 0 | C77: =SUMPRODUCT(('Headcount Calc'!$B$6:$B$83=$A$71)*('Headcount Calc'!$C$6:$C$83="Open role")*('Headcount Calc'!$H$6:$H$83=1)*('Headcount Calc'!$F$6:$F$83>=C$4)*('Headcount Calc'!$F$6:$F$83<=EOMONTH(C$4,0))*'Headcount Calc'!$E$6:$E$83)*Assumptions!$B$19+SUMPRODUCT(('Headcount Calc'!$B$6:$B$83=$A$71)*('Headcount Calc'!$C$6:$C$83="Open role")*('Headcount Calc'!$H$6:$H$83=1)*('Headcount Calc'!$F$6:$F$83>=C$4)*('Headcount Calc'!$F$6:$F$83<=EOMONTH(C$4,0)))*Assumptions!$B$20 -> 21075 | D77: =SUMPRODUCT(('Headcount Calc'!$B$6:$B$83=$A$71)*('Headcount Calc'!$C$6:$C$83="Open role")*('Headcount Calc'!$H$6:$H$83=1)*('Headcount Calc'!$F$6:$F$83>=D$4)*('Headcount Calc'!$F$6:$F$83<=EOMONTH(D$4,0))*'Headcount Calc'!$E$6:$E$83)*Assumptions!$B$19+SUMPRODUCT(('Headcount Calc'!$B$6:$B$83=$A$71)*('Headcount Calc'!$C$6:$C$83="Open role")*('Headcount Calc'!$H$6:$H$83=1)*('Headcount Calc'!$F$6:$F$83>=D$4)*('Headcount Calc'!$F$6:$F$83<=EOMONTH(D$4,0)))*Assumptions!$B$20 -> 0 | E77: =SUMPRODUCT(('Headcount Calc'!$B$6:$B$83=$A$71)*('Headcount Calc'!$C$6:$C$83="Open role")*('Headcount Calc'!$H$6:$H$83=1)*('Headcount Calc'!$F$6:$F$83>=E$4)*('Headcount Calc'!$F$6:$F$83<=EOMONTH(E$4,0))*'Headcount Calc'!$E$6:$E$83)*Assumptions!$B$19+SUMPRODUCT(('Headcount Calc'!$B$6:$B$83=$A$71)*('Headcount Calc'!$C$6:$C$83="Open role")*('Headcount Calc'!$H$6:$H$83=1)*('Headcount Calc'!$F$6:$F$83>=E$4)*('Headcount Calc'!$F$6:$F$83<=EOMONTH(E$4,0)))*Assumptions!$B$20 -> 0 | F77: =SUMPRODUCT(('Headcount Calc'!$B$6:$B$83=$A$71)*('Headcount Calc'!$C$6:$C$83="Open role")*('Headcount Calc'!$H$6:$H$83=1)*('Headcount Calc'!$F$6:$F$83>=F$4)*('Headcount Calc'!$F$6:$F$83<=EOMONTH(F$4,0))*'Headcount Calc'!$E$6:$E$83)*Assumptions!$B$19+SUMPRODUCT(('Headcount Calc'!$B$6:$B$83=$A$71)*('Headcount Calc'!$C$6:$C$83="Open role")*('Headcount Calc'!$H$6:$H$83=1)*('Headcount Calc'!$F$6:$F$83>=F$4)*('Headcount Calc'!$F$6:$F$83<=EOMONTH(F$4,0)))*Assumptions!$B$20 -> 0 | G77: =SUMPRODUCT(('Headcount Calc'!$B$6:$B$83=$A$71)*('Headcount Calc'!$C$6:$C$83="Open role")*('Headcount Calc'!$H$6:$H$83=1)*('Headcount Calc'!$F$6:$F$83>=G$4)*('Headcount Calc'!$F$6:$F$83<=EOMONTH(G$4,0))*'Headcount Calc'!$E$6:$E$83)*Assumptions!$B$19+SUMPRODUCT(('Headcount Calc'!$B$6:$B$83=$A$71)*('Headcount Calc'!$C$6:$C$83="Open role")*('Headcount Calc'!$H$6:$H$83=1)*('Headcount Calc'!$F$6:$F$83>=G$4)*('Headcount Calc'!$F$6:$F$83<=EOMONTH(G$4,0)))*Assumptions!$B$20 -> 16950 | H77: =SUMPRODUCT(('Headcount Calc'!$B$6:$B$83=$A$71)*('Headcount Calc'!$C$6:$C$83="Open role")*('Headcount Calc'!$H$6:$H$83=1)*('Headcount Calc'!$F$6:$F$83>=H$4)*('Headcount Calc'!$F$6:$F$83<=EOMONTH(H$4,0))*'Headcount Calc'!$E$6:$E$83)*Assumptions!$B$19+SUMPRODUCT(('Headcount Calc'!$B$6:$B$83=$A$71)*('Headcount Calc'!$C$6:$C$83="Open role")*('Headcount Calc'!$H$6:$H$83=1)*('Headcount Calc'!$F$6:$F$83>=H$4)*('Headcount Calc'!$F$6:$F$83<=EOMONTH(H$4,0)))*Assumptions!$B$20 -> 0 | I77: =SUMPRODUCT(('Headcount Calc'!$B$6:$B$83=$A$71)*('Headcount Calc'!$C$6:$C$83="Open role")*('Headcount Calc'!$H$6:$H$83=1)*('Headcount Calc'!$F$6:$F$83>=I$4)*('Headcount Calc'!$F$6:$F$83<=EOMONTH(I$4,0))*'Headcount Calc'!$E$6:$E$83)*Assumptions!$B$19+SUMPRODUCT(('Headcount Calc'!$B$6:$B$83=$A$71)*('Headcount Calc'!$C$6:$C$83="Open role")*('Headcount Calc'!$H$6:$H$83=1)*('Headcount Calc'!$F$6:$F$83>=I$4)*('Headcount Calc'!$F$6:$F$83<=EOMONTH(I$4,0)))*Assumptions!$B$20 -> 0 | ... M77: =SUMPRODUCT(('Headcount Calc'!$B$6:$B$83=$A$71)*('Headcount Calc'!$C$6:$C$83="Open role")*('Headcount Calc'!$H$6:$H$83=1)*('Headcount Calc'!$F$6:$F$83>=M$4)*('Headcount Calc'!$F$6:$F$83<=EOMONTH(M$4,0))*'Headcount Calc'!$E$6:$E$83)*Assumptions!$B$19+SUMPRODUCT(('Headcount Calc'!$B$6:$B$83=$A$71)*('Headcount Calc'!$C$6:$C$83="Open role")*('Headcount Calc'!$H$6:$H$83=1)*('Headcount Calc'!$F$6:$F$83>=M$4)*('Headcount Calc'!$F$6:$F$83<=EOMONTH(M$4,0)))*Assumptions!$B$20 -> 0 | N77: =SUM(B77:M77) -> 38025
A78: Software & tools | B78: =B72*Assumptions!$B$21 -> 2000 | C78: =C72*Assumptions!$B$21 -> 2250 | D78: =D72*Assumptions!$B$21 -> 2250 | E78: =E72*Assumptions!$B$21 -> 2250 | F78: =F72*Assumptions!$B$21 -> 2250 | G78: =G72*Assumptions!$B$21 -> 2500 | H78: =H72*Assumptions!$B$21 -> 2500 | I78: =I72*Assumptions!$B$21 -> 2500 | ... M78: =M72*Assumptions!$B$21 -> 2500 | N78: =SUM(B78:M78) -> 28500
A79: Travel & entertainment | B79: =B72*VLOOKUP($A$71,Assumptions!$A$35:$C$40,2,FALSE()) -> 1200 | C79: =C72*VLOOKUP($A$71,Assumptions!$A$35:$C$40,2,FALSE()) -> 1350 | D79: =D72*VLOOKUP($A$71,Assumptions!$A$35:$C$40,2,FALSE()) -> 1350 | E79: =E72*VLOOKUP($A$71,Assumptions!$A$35:$C$40,2,FALSE()) -> 1350 | F79: =F72*VLOOKUP($A$71,Assumptions!$A$35:$C$40,2,FALSE()) -> 1350 | G79: =G72*VLOOKUP($A$71,Assumptions!$A$35:$C$40,2,FALSE()) -> 1500 | H79: =H72*VLOOKUP($A$71,Assumptions!$A$35:$C$40,2,FALSE()) -> 1500 | I79: =I72*VLOOKUP($A$71,Assumptions!$A$35:$C$40,2,FALSE()) -> 1500 | ... M79: =M72*VLOOKUP($A$71,Assumptions!$A$35:$C$40,2,FALSE()) -> 1500 | N79: =SUM(B79:M79) -> 17100
A80: Facilities | B80: =B72*Assumptions!$B$22 -> 4800 | C80: =C72*Assumptions!$B$22 -> 5400 | D80: =D72*Assumptions!$B$22 -> 5400 | E80: =E72*Assumptions!$B$22 -> 5400 | F80: =F72*Assumptions!$B$22 -> 5400 | G80: =G72*Assumptions!$B$22 -> 6000 | H80: =H72*Assumptions!$B$22 -> 6000 | I80: =I72*Assumptions!$B$22 -> 6000 | ... M80: =M72*Assumptions!$B$22 -> 6000 | N80: =SUM(B80:M80) -> 68400
A81: Programs & vendors | B81: =VLOOKUP($A$71,Assumptions!$A$35:$C$40,3,FALSE())/12*(1+Assumptions!$F$11) -> 75000 | C81: =VLOOKUP($A$71,Assumptions!$A$35:$C$40,3,FALSE())/12*(1+Assumptions!$F$11) -> 75000 | D81: =VLOOKUP($A$71,Assumptions!$A$35:$C$40,3,FALSE())/12*(1+Assumptions!$F$11) -> 75000 | E81: =VLOOKUP($A$71,Assumptions!$A$35:$C$40,3,FALSE())/12*(1+Assumptions!$F$11) -> 75000 | F81: =VLOOKUP($A$71,Assumptions!$A$35:$C$40,3,FALSE())/12*(1+Assumptions!$F$11) -> 75000 | G81: =VLOOKUP($A$71,Assumptions!$A$35:$C$40,3,FALSE())/12*(1+Assumptions!$F$11) -> 75000 | H81: =VLOOKUP($A$71,Assumptions!$A$35:$C$40,3,FALSE())/12*(1+Assumptions!$F$11) -> 75000 | I81: =VLOOKUP($A$71,Assumptions!$A$35:$C$40,3,FALSE())/12*(1+Assumptions!$F$11) -> 75000 | ... M81: =VLOOKUP($A$71,Assumptions!$A$35:$C$40,3,FALSE())/12*(1+Assumptions!$F$11) -> 75000 | N81: =SUM(B81:M81) -> 900000
A82: Total operating expense | B82: =SUM(B73:B81) -> 185359.03 | C82: =SUM(C73:C81) -> 220425.17 | D82: =SUM(D73:D81) -> 199350.17 | E82: =SUM(E73:E81) -> 202610.73 | F82: =SUM(F73:F81) -> 202610.73 | G82: =SUM(G73:G81) -> 230683.37 | H82: =SUM(H73:H81) -> 213733.37 | I82: =SUM(I73:I81) -> 213733.37 | ... M82: =SUM(M73:M81) -> 213733.37 | N82: =SUM(B82:M82) -> 2523439.4
A84: TOTAL COMPANY
A85: FTE (average for the month) | B85: =B7+B20+B33+B46+B59+B72 -> 60 | C85: =C7+C20+C33+C46+C59+C72 -> 62 | D85: =D7+D20+D33+D46+D59+D72 -> 64 | E85: =E7+E20+E33+E46+E59+E72 -> 66 | F85: =F7+F20+F33+F46+F59+F72 -> 67 | G85: =G7+G20+G33+G46+G59+G72 -> 70 | H85: =H7+H20+H33+H46+H59+H72 -> 71 | I85: =I7+I20+I33+I46+I59+I72 -> 71 | ... M85: =M7+M20+M33+M46+M59+M72 -> 71 | N85: =AVERAGE(B85:M85) -> 67.916667
A86: Salaries | B86: =B8+B21+B34+B47+B60+B73 -> 575083.33 | C86: =C8+C21+C34+C47+C60+C73 -> 594125 | D86: =D8+D21+D34+D47+D60+D73 -> 612416.67 | E86: =E8+E21+E34+E47+E60+E73 -> 649086.25 | F86: =F8+F21+F34+F47+F60+F73 -> 655181.67 | G86: =G8+G21+G34+G47+G60+G73 -> 682181.67 | H86: =H8+H21+H34+H47+H60+H73 -> 697913.96 | I86: =I8+I21+I34+I47+I60+I73 -> 697913.96 | ... N86: =N8+N21+N34+N47+N60+N73 -> 7955685.8
A87: Bonus & variable compensation | B87: =B9+B22+B35+B48+B61+B74 -> 82035.417 | C87: =C9+C22+C35+C48+C61+C74 -> 83759.583 | D87: =D9+D22+D35+D48+D61+D74 -> 86922.083 | E87: =E9+E22+E35+E48+E61+E74 -> 91116.656 | F87: =F9+F22+F35+F48+F61+F74 -> 91592.865 | G87: =G9+G22+G35+G48+G61+G74 -> 95487.865 | H87: =H9+H22+H35+H48+H61+H74 -> 97882.552 | I87: =I9+I22+I35+I48+I61+I74 -> 97882.552 | ... N87: =N9+N22+N35+N48+N61+N74 -> 1118216.2
A88: Payroll taxes | B88: =B10+B23+B36+B49+B62+B75 -> 47312.55 | C88: =C10+C23+C36+C49+C62+C75 -> 48807.69 | D88: =D10+D23+D36+D49+D62+D75 -> 50352.39 | E88: =E10+E23+E36+E49+E62+E75 -> 53294.609 | F88: =F10+F23+F36+F49+F62+F75 -> 53767.766 | G88: =G10+G23+G36+G49+G62+G75 -> 55992.206 | H88: =H10+H23+H36+H49+H62+H75 -> 57297.349 | I88: =I10+I23+I36+I49+I62+I75 -> 57297.349 | ... N88: =N10+N23+N36+N49+N62+N75 -> 653320.94
A89: Benefits | B89: =B11+B24+B37+B50+B63+B76 -> 69000 | C89: =C11+C24+C37+C50+C63+C76 -> 71300 | D89: =D11+D24+D37+D50+D63+D76 -> 73600 | E89: =E11+E24+E37+E50+E63+E76 -> 75900 | F89: =F11+F24+F37+F50+F63+F76 -> 77050 | G89: =G11+G24+G37+G50+G63+G76 -> 80500 | H89: =H11+H24+H37+H50+H63+H76 -> 81650 | I89: =I11+I24+I37+I50+I63+I76 -> 81650 | ... N89: =N11+N24+N37+N50+N63+N76 -> 937250
A90: Recruiting & onboarding | B90: =B12+B25+B38+B51+B64+B77 -> 0 | C90: =C12+C25+C38+C51+C64+C77 -> 40275 | D90: =D12+D25+D38+D51+D64+D77 -> 38925 | E90: =E12+E25+E38+E51+E64+E77 -> 35775 | F90: =F12+F25+F38+F51+F64+F77 -> 40725 | G90: =G12+G25+G38+G51+G64+G77 -> 57600 | H90: =H12+H25+H38+H51+H64+H77 -> 46350 | I90: =I12+I25+I38+I51+I64+I77 -> 0 | ... N90: =N12+N25+N38+N51+N64+N77 -> 272100
A91: Software & tools | B91: =B13+B26+B39+B52+B65+B78 -> 15000 | C91: =C13+C26+C39+C52+C65+C78 -> 15500 | D91: =D13+D26+D39+D52+D65+D78 -> 16000 | E91: =E13+E26+E39+E52+E65+E78 -> 16500 | F91: =F13+F26+F39+F52+F65+F78 -> 16750 | G91: =G13+G26+G39+G52+G65+G78 -> 17500 | H91: =H13+H26+H39+H52+H65+H78 -> 17750 | I91: =I13+I26+I39+I52+I65+I78 -> 17750 | ... N91: =N13+N26+N39+N52+N65+N78 -> 203750
A92: Travel & entertainment | B92: =B14+B27+B40+B53+B66+B79 -> 23800 | C92: =C14+C27+C40+C53+C66+C79 -> 24100 | D92: =D14+D27+D40+D53+D66+D79 -> 25500 | E92: =E14+E27+E40+E53+E66+E79 -> 26050 | F92: =F14+F27+F40+F53+F66+F79 -> 26250 | G92: =G14+G27+G40+G53+G66+G79 -> 27750 | H92: =H14+H27+H40+H53+H66+H79 -> 27900 | I92: =I14+I27+I40+I53+I66+I79 -> 27900 | ... N92: =N14+N27+N40+N53+N66+N79 -> 320850
A93: Facilities | B93: =B15+B28+B41+B54+B67+B80 -> 36000 | C93: =C15+C28+C41+C54+C67+C80 -> 37200 | D93: =D15+D28+D41+D54+D67+D80 -> 38400 | E93: =E15+E28+E41+E54+E67+E80 -> 39600 | F93: =F15+F28+F41+F54+F67+F80 -> 40200 | G93: =G15+G28+G41+G54+G67+G80 -> 42000 | H93: =H15+H28+H41+H54+H67+H80 -> 42600 | I93: =I15+I28+I41+I54+I67+I80 -> 42600 | ... N93: =N15+N28+N41+N54+N67+N80 -> 489000
A94: Programs & vendors | B94: =B16+B29+B42+B55+B68+B81 -> 287500 | C94: =C16+C29+C42+C55+C68+C81 -> 287500 | D94: =D16+D29+D42+D55+D68+D81 -> 287500 | E94: =E16+E29+E42+E55+E68+E81 -> 287500 | F94: =F16+F29+F42+F55+F68+F81 -> 287500 | G94: =G16+G29+G42+G55+G68+G81 -> 287500 | H94: =H16+H29+H42+H55+H68+H81 -> 287500 | I94: =I16+I29+I42+I55+I68+I81 -> 287500 | ... N94: =N16+N29+N42+N55+N68+N81 -> 3450000
A95: Total operating expense | B95: =B17+B30+B43+B56+B69+B82 -> 1135731.3 | C95: =C17+C30+C43+C56+C69+C82 -> 1202567.3 | D95: =D17+D30+D43+D56+D69+D82 -> 1229616.1 | E95: =E17+E30+E43+E56+E69+E82 -> 1274822.5 | F95: =F17+F30+F43+F56+F69+F82 -> 1289017.3 | G95: =G17+G30+G43+G56+G69+G82 -> 1346511.7 | H95: =H17+H30+H43+H56+H69+H82 -> 1356843.9 | I95: =I17+I30+I43+I56+I69+I82 -> 1310493.9 | ... N95: =N17+N30+N43+N56+N69+N82 -> 15400173
A96: Check: department lines sum to total (should be 0) | N96: =ROUND(SUM(N86:N94)-N95,0) -> 0

Sheet Summary
A1: FY2027 Budget Summary
A2: ="Scenario: "&Assumptions!$C$5&" | Brightwater Analytics, Inc. (simulated)" -> Scenario: Plan | Brightwater Analytics, Inc. (simulated)
A4: Department | B4: FY2026 actual opex ($) | C4: FY2027 budget ($) | D4: Change ($) | E4: Change (%) | F4: Headcount Jan 1 | G4: Headcount Dec 31 | H4: Net adds | I4: Cost per avg. FTE ($)
A5: Engineering | B5: 4326000 | C5: ='Department Budget'!N17 -> 5018288.1 | D5: =C5-B5 -> 692288.12 | E5: =IF(B5=0,0,C5/B5-1) -> 0.16002962 | F5: =SUMIF('Headcount Calc'!$B$6:$B$83,A5,'Headcount Calc'!$K$6:$K$83) -> 20 | G5: =SUMIF('Headcount Calc'!$B$6:$B$83,A5,'Headcount Calc'!$V$6:$V$83) -> 24 | H5: =G5-F5 -> 4 | I5: =C5/'Department Budget'!N7 -> 220584.09
A6: Product | B6: 1182000 | C6: ='Department Budget'!N30 -> 1323535.6 | D6: =C6-B6 -> 141535.62 | E6: =IF(B6=0,0,C6/B6-1) -> 0.11974248 | F6: =SUMIF('Headcount Calc'!$B$6:$B$83,A6,'Headcount Calc'!$K$6:$K$83) -> 5 | G6: =SUMIF('Headcount Calc'!$B$6:$B$83,A6,'Headcount Calc'!$V$6:$V$83) -> 6 | H6: =G6-F6 -> 1 | I6: =C6/'Department Budget'!N20 -> 226891.82
A7: Sales | B7: 2183000 | C7: ='Department Budget'!N43 -> 2619009.9 | D7: =C7-B7 -> 436009.89 | E7: =IF(B7=0,0,C7/B7-1) -> 0.19972968 | F7: =SUMIF('Headcount Calc'!$B$6:$B$83,A7,'Headcount Calc'!$K$6:$K$83) -> 12 | G7: =SUMIF('Headcount Calc'!$B$6:$B$83,A7,'Headcount Calc'!$V$6:$V$83) -> 14 | H7: =G7-F7 -> 2 | I7: =C7/'Department Budget'!N33 -> 195205.71
A8: Marketing | B8: 2309000 | C8: ='Department Budget'!N56 -> 2539442.9 | D8: =C8-B8 -> 230442.92 | E8: =IF(B8=0,0,C8/B8-1) -> 0.099802045 | F8: =SUMIF('Headcount Calc'!$B$6:$B$83,A8,'Headcount Calc'!$K$6:$K$83) -> 6 | G8: =SUMIF('Headcount Calc'!$B$6:$B$83,A8,'Headcount Calc'!$V$6:$V$83) -> 7 | H8: =G8-F8 -> 1 | I8: =C8/'Department Budget'!N46 -> 376213.77
A9: Customer Success | B9: 1274000 | C9: ='Department Budget'!N69 -> 1376456.9 | D9: =C9-B9 -> 102456.94 | E9: =IF(B9=0,0,C9/B9-1) -> 0.080421463 | F9: =SUMIF('Headcount Calc'!$B$6:$B$83,A9,'Headcount Calc'!$K$6:$K$83) -> 9 | G9: =SUMIF('Headcount Calc'!$B$6:$B$83,A9,'Headcount Calc'!$V$6:$V$83) -> 10 | H9: =G9-F9 -> 1 | I9: =C9/'Department Budget'!N59 -> 142392.1
A10: G&A | B10: 2381000 | C10: ='Department Budget'!N82 -> 2523439.4 | D10: =C10-B10 -> 142439.44 | E10: =IF(B10=0,0,C10/B10-1) -> 0.059823369 | F10: =SUMIF('Headcount Calc'!$B$6:$B$83,A10,'Headcount Calc'!$K$6:$K$83) -> 8 | G10: =SUMIF('Headcount Calc'!$B$6:$B$83,A10,'Headcount Calc'!$V$6:$V$83) -> 10 | H10: =G10-F10 -> 2 | I10: =C10/'Department Budget'!N72 -> 265625.2
A11: Total company | B11: =SUM(B5:B10) -> 13655000 | C11: =SUM(C5:C10) -> 15400173 | D11: =SUM(D5:D10) -> 1745172.9 | E11: =IF(B11=0,0,C11/B11-1) -> 0.12780468 | F11: =SUM(F5:F10) -> 60 | G11: =SUM(G5:G10) -> 71 | H11: =SUM(H5:H10) -> 11 | I11: =C11/'Department Budget'!N85 -> 226751.01
A12: FY2026 actual opex is simulated prior-year data for comparison. Headcount = FTE in January and December.
A14: BUDGET VS. TARGETS
A15: Total FY2027 operating expense | B15: =C11 -> 15400173
A16: Leadership opex ceiling | B16: =Assumptions!$B$45 -> 15000000
A17: Over / (under) ceiling | B17: =B15-B16 -> 400172.93
A18: FY2027 revenue plan | B18: =Assumptions!$B$43 -> 19500000
A19: Opex as % of revenue — FY2027 | B19: =B15/B18 -> 0.78975246
A20: Opex as % of revenue — FY2026 | B20: =B11/Assumptions!$B$44 -> 0.91033333
A21: Revenue growth | B21: =Assumptions!$B$43/Assumptions!$B$44-1 -> 0.3
A22: Opex growth | B22: =E11 -> 0.12780468
A23: People costs as % of opex | B23: =SUM('Department Budget'!N86:N89)/'Department Budget'!N95 -> 0.69249047
A24: New hires in plan | B24: =SUMPRODUCT(('Headcount Calc'!$C$6:$C$83="Open role")*'Headcount Calc'!$H$6:$H$83) -> 14
A25: Departures | B25: =COUNTIFS('Headcount Calc'!$C$6:$C$83,"Existing",'Headcount Calc'!$G$6:$G$83,"<"&DATE(2099,1,1)) -> 3

Sheet Scenarios
A1: Scenario Comparison
A2: Snapshot captured by recalculating with Assumptions!B5 = 1 to 4. Change B5 to see any scenario live.
A4: Output | B4: Plan | C4: Hiring freeze | D4: Accelerated growth | E4: Deferred hiring
A5: Total operating expense ($) | B5: 15400173 | C5: 13855846 | D5: 16176756 | E5: 14893456
A6: Over / (under) leadership ceiling ($) | B6: 400172.93 | C6: -1144154.3 | D6: 1176756.4 | E6: -106544.23
A7: Opex as % of revenue | B7: 0.78975246 | C7: 0.71055619 | D7: 0.82957725 | E7: 0.76376696
A8: Opex growth vs. FY2026 | B8: 0.12780468 | C8: 0.014708585 | D8: 0.18467641 | E8: 0.090696139
A9: New hires | B9: 14 | C9: 6 | D9: 18 | E9: 14
A10: Headcount Dec 31 | B10: 71 | C10: 63 | D10: 75 | E10: 71
A11: Average FTE | B11: 67.916667 | C11: 62.666667 | D11: 70.75 | E11: 65.916667
A12: Salaries + bonus ($) | B12: 9073902 | C12: 8404427 | D12: 9348140.3 | E12: 8814184.5
A13: Recruiting & onboarding ($) | B13: 272100 | C13: 108900 | D13: 326100 | E13: 272100
A14: Programs & vendors ($) | B14: 3450000 | C14: 2932500 | D14: 3795000 | E14: 3277500
A15: Change in opex vs. Plan ($) | B15: 0 | C15: -1544327.2 | D15: 776583.49 | E15: -506717.16
A17: Scenario definitions (Assumptions rows 8–11):
A18: Plan: priority 1–2 roles hired on planned dates; programs at budget.
A19: Hiring freeze: only priority 1 (critical and backfill) roles; programs and vendors cut 15%.
A20: Accelerated growth: all roles including priority 3, start dates pulled forward one month; programs +10%.
A21: Deferred hiring: all priority 1–2 roles kept, priority 2 start dates delayed one quarter; programs and vendors cut 5%.
